Workbook

Sheet Profile
A1: Onboarding | B1: Category | C1: Profile question | D1: P-text | E1: Profile answer | F1: Goal tag | G1: Life moment | H1: Content tag 1 (topic) | I1: Content tag 2 (group) | J1: Profile tag | K1: web Video/reel | L1: Mobile Video/reel | M1: Notes
A2: Onboarding | B2: circumstances | C2: Who do you include in your budget? | D2: Choose everyone you feel responsible for when planning your finances. | E2: Myself | F2: goal-retirement, goal-emergency-fund | I2: group-family | J2: profile-family-myself | K2: https://videos.ctfassets.net/pmoql4aw53io/fLHvCorN4uCZI7vL13FNe/fe0f5f334c47343d9ab3728401d69eee/onb_web_benefits.mp4 | L2: retirement video
A3: Onboarding | B3: circumstances | C3: Who do you include in your budget? | D3: Choose everyone you feel responsible for when planning your finances. | E3: Spouse/partner | G3: lm-combining-finances | H3: topic-partner | I3: group-family | J3: profile-family-spouse | K3: https://videos.ctfassets.net/pmoql4aw53io/MuB3xyTncjpeIG3yDGXMN/c87d6d0b6fdd052f55bfabdb4b011cf1/onb_web_budged.mp4 | L3: Budget video
A4: Onboarding | B4: circumstances | C4: Who do you include in your budget? | D4: Choose everyone you feel responsible for when planning your finances. | E4: Kids | F4: goal-kids-education | G4: lm-growing-your-family | H4: topic-kids | I4: group-family | J4: profile-family-havekids | K4: https://videos.ctfassets.net/pmoql4aw53io/fLHvCorN4uCZI7vL13FNe/fe0f5f334c47343d9ab3728401d69eee/onb_web_benefits.mp4 | L4: retirement video
A5: Onboarding | B5: circumstances | C5: Who do you include in your budget? | D5: Choose everyone you feel responsible for when planning your finances. | E5: Extended family | H5: topic-caregiving | I5: group-family | J5: profile-family-extendedfam
A6: Onboarding | B6: circumstances | C6: Who do you include in your budget? | D6: Choose everyone you feel responsible for when planning your finances. | E6: Parents | H6: topic-caregiving | I6: group-family | J6: profile-family-agingparents | K6: https://videos.ctfassets.net/pmoql4aw53io/fLHvCorN4uCZI7vL13FNe/fe0f5f334c47343d9ab3728401d69eee/onb_web_benefits.mp4 | L6: retirement video
A7: Onboarding | B7: circumstances | C7: Who do you include in your budget? | D7: Choose everyone you feel responsible for when planning your finances. | E7: Pets | H7: topic-pets | I7: group-family | J7: profile-family-havepets
A8: Onboarding | B8: circumstances | C8: Do you rent or own your home? | D8: A home could be a house, condo, apartment, or something else -- wherever you live! | E8: Own | H8: topic-owning-home | I8: group-housing | J8: profile-property-ownhome | K8: https://videos.ctfassets.net/pmoql4aw53io/fLHvCorN4uCZI7vL13FNe/fe0f5f334c47343d9ab3728401d69eee/onb_web_benefits.mp4 | L8: benefits
A9: Onboarding | B9: circumstances | C9: Do you rent or own your home? | D9: A home could be a house, condo, apartment, or something else -- wherever you live! | E9: Rent | F9: goal-buying-a-home | H9: topic-renting | I9: group-housing | J9: profile-property-rent | K9: Buying a Home video
A10: Onboarding | B10: circumstances | C10: Do you rent or own your home? | D10: A home could be a house, condo, apartment, or something else -- wherever you live! | E10: Neither | F10: goal-buying-a-home | H10: topic-free-housing | I10: group-housing | J10: profile-property-neither | M10: https://videos.ctfassets.net/pmoql4aw53io/fLHvCorN4uCZI7vL13FNe/fe0f5f334c47343d9ab3728401d69eee/onb_web_benefits.mp4 | N10: Benefits video
A11: Onboarding | B11: priorities | C11: What are your financial priorities? | D11: We'll connect you with information and benefits to help. | E11: Budgeting | F11: goal-emergency-fund | H11: topic-budget | I11: group-how-to-save | J11: profile-priorities-budgeting | K11: https://videos.ctfassets.net/pmoql4aw53io/MuB3xyTncjpeIG3yDGXMN/c87d6d0b6fdd052f55bfabdb4b011cf1/onb_web_budged.mp4 | L11: Budget video
A12: Onboarding | B12: priorities | C12: What are your financial priorities? | D12: We'll connect you with information and benefits to help. | E12: Buying a home | F12: goal-buying-a-home | H12: topic-mortgages | I12: group-housing | J12: profile-priorities-wanthome | K12: https://videos.ctfassets.net/pmoql4aw53io/XUE1VbhOE88IWPWawhLxZ/20f0337d8957ddadfdd028699e7b66f8/onb_web_buy_home.mp4 | L12: Buy home video
A13: Onboarding | B13: priorities | C13: What are your financial priorities? | D13: We'll connect you with information and benefits to help. | E13: College fund | F13: goal-kids-education | H13: topic-529 | I13: group-how-to-save | J13: profile-priorities-collegefund
A14: Onboarding | B14: priorities | C14: What are your financial priorities? | D14: We'll connect you with information and benefits to help. | E14: Estate planning | H14: topic-estate-planning | I14: group-benefits | J14: profile-priorities-budgeting
A15: Onboarding | B15: priorities | C15: What are your financial priorities? | D15: We'll connect you with information and benefits to help. | E15: Health costs | H15: topic-health | I15: group-benefits | J15: profile-priorities-healthcost
A16: Onboarding | B16: priorities | C16: What are your financial priorities? | D16: We'll connect you with information and benefits to help. | E16: Investing | H16: topic-investing | I16: group-investing-strategies | J16: profile-priorities-investing | K16: https://videos.ctfassets.net/pmoql4aw53io/4nSxcJwGTfzy1PfjnZM4FB/9c1b4067e968ad1960ea46cd7cce7eb2/onb_web_occams.mp4 | L16: Occam's
A17: Onboarding | B17: priorities | C17: What are your financial priorities? | D17: We'll connect you with information and benefits to help. | E17: Life insurance | H17: topic-insurance | I17: group-account-types | J17: profile-priorities-lifeinsurance
A18: Onboarding | B18: priorities | C18: What are your financial priorities? | D18: We'll connect you with information and benefits to help. | E18: Managing debt | F18: goal-debt-management | H18: topic-credit-cards | I18: group-account-types | J18: profile-priorities-debtmanagement | K18: https://videos.ctfassets.net/pmoql4aw53io/6Q4vuk0UDEcJgjVrcsscBF/242e3d1465526dad0ab5cc13ba27d545/onb_web_debt.mp4 | L18: Debt video
A19: Onboarding | B19: priorities | C19: What are your financial priorities? | D19: We'll connect you with information and benefits to help. | E19: Tax planning | H19: topic-taxes | I19: group-benefits | J19: profile-priorities-taxplanning
A20: Onboarding | B20: priorities | C20: What are your financial priorities? | D20: We'll connect you with information and benefits to help. | E20: Retirement | F20: goal-retirement | H20: topic-retirement | I20: group-account-types | J20: profile-property-retirement | K20: https://videos.ctfassets.net/pmoql4aw53io/fLHvCorN4uCZI7vL13FNe/fe0f5f334c47343d9ab3728401d69eee/onb_web_benefits.mp4 | L20: Occam's
A22: Launch questions below
A23: Profile | B23: circumstances | C23: What insurance policies do you have? | D23: Select all types that you carry currently. | E23: Disability | H23: topic-insurance | I23: group-protecting-wealth | J23: profile-disability-insurance
A24: Profile | B24: circumstances | C24: What insurance policies do you have? | D24: Select all types that you carry currently. | E24: Life | H24: topic-insurance | I24: group-protecting-wealth | J24: profile-life-insurance
A25: Profile | B25: circumstances | C25: What insurance policies do you have? | D25: Select all types that you carry currently. | E25: Home | H25: topic-insurance | I25: group-protecting-wealth | J25: profile-home-insurance
A26: Profile | B26: circumstances | C26: What insurance policies do you have? | D26: Select all types that you carry currently. | E26: Renters | H26: topic-insurance | I26: group-protecting-wealth | J26: profile-renters-insurance
A27: Profile | B27: circumstances | C27: What insurance policies do you have? | D27: Select all types that you carry currently. | E27: Umbrella | H27: topic-insurance | I27: group-protecting-wealth | J27: profile-umbrella-insurance
A28: Profile | B28: circumstances | C28: What estate plans have you put in place? | D28: Select everything you've planned for your finances after death. | E28: Will | H28: topic-estate-planning | I28: group-protecting-wealth | J28: profile-will
A29: Profile | B29: circumstances | C29: What estate plans have you put in place? | D29: Select everything you've planned for your finances after death. | E29: Trust | H29: topic-estate-planning | I29: group-caregiving | J29: profile-trust
A30: Profile | B30: circumstances | C30: What estate plans have you put in place? | D30: Select everything you've planned for your finances after death. | E30: Guardianship | H30: topic-estate-planning | I30: group-protecting-wealth | J30: profile-guardianship
A31: Profile | B31: circumstances | C31: What estate plans have you put in place? | D31: Select everything you've planned for your finances after death. | E31: Beneficiaries | H31: topic-beneficiaries | I31: group-protecting-wealth | J31: profile-beneficiaries
A32: Profile | B32: preferences | C32: How often do you want to review progress on your financial goals? | D32: Choose the answer that feels right for your needs. | E32: Never | H32: topic-goals | I32: group-priorities | J32: profile-goal-progress-never
A33: Profile | B33: preferences | C33: How often do you want to review progress on your financial goals? | D33: Choose the answer that feels right for your needs. | E33: Yearly | H33: topic-goals | I33: group-priorities | J33: profile-goal-progress-yearly
A34: Profile | B34: preferences | C34: How often do you want to review progress on your financial goals? | D34: Choose the answer that feels right for your needs. | E34: Quarterly | H34: topic-goals | I34: group-priorities | J34: profile-goal-progress-quarterly
... A39: Profile | B39: confidence & clarity | C39: What’s your investment experience level? | D39: Select the best answer to describe yourself. | E39: Intermediate | H39: topic-investing | I39: group-investing-strategies | J39: profile-invest-intermediate
B40: confidence & clarity | C40: What’s your investment experience level? | D40: Select the best answer to describe yourself. | E40: Advanced | H40: topic-investing | I40: group-investing-strategies | J40: profile-invest-advanced
A41: Profile | B41: confidence & clarity | C41: What’s your investment experience level? | D41: Select the best answer to describe yourself. | E41: None | H41: topic-investing | I41: group-investing-strategies | J41: profile-invest-none
A42: Draft below
A43: Profile | C43: In managing your finances, which professionals do you collaborate with? | D43: Select all that you've used recently or in the past. | E43: Stock broker | I43: group-investing-strategies | J43: profile-investhelp-stockbroker
A44: Profile | C44: In managing your finances, which professionals do you collaborate with? | D44: Select all that you've used recently or in the past. | E44: Investment banker | I44: group-investing-strategies | J44: profile-investhelp-investmentbanker
A45: Profile | C45: In managing your finances, which professionals do you collaborate with? | D45: Select all that you've used recently or in the past. | E45: Financial planner | I45: group-investing-strategies | J45: profile-investhelp-financialadvisor
A46: Profile | C46: In managing your finances, which professionals do you collaborate with? | D46: Select all that you've used recently or in the past. | E46: Robo-advisor | I46: group-investing-strategies | J46: profile-investhelp-roboadvisor
A47: Profile | C47: In managing your finances, which professionals do you collaborate with? | D47: Select all that you've used recently or in the past. | E47: Tax accountant | I47: group-investing-strategies | J47: profile-investhelp-taxaccountant
A48: Profile | C48: In managing your finances, which professionals do you collaborate with? | D48: Select all that you've used recently or in the past. | E48: Estate attorney | I48: group-investing-strategies | J48: profile-investhelp-estateattorney
A49: Profile | B49: confidence & clarity | C49: What’s your comfort level with risk when investing? | D49: Tell us how much risk you're comfortable with. | E49: High | H49: topic-risk-high | I49: group-risk-levels | J49: profile-risk-high
A50: Profile | B50: confidence & clarity | C50: What’s your comfort level with risk when investing? | D50: Tell us how much risk you're comfortable with. | E50: Medium | H50: topic-risk-medium | I50: group-risk-levels | J50: profile-risk-medium
A51: Profile | B51: confidence & clarity | C51: What’s your comfort level with risk when investing? | D51: Tell us how much risk you're comfortable with. | E51: Low | H51: topic-risk-low | I51: group-risk-levels | J51: profile-risk-low
A52: Profile | B52: circumstances | C52: Do you have a life insurance policy for yourself? | E52: No, I don't need it
A53: Profile | B53: circumstances | C53: Do you have a life insurance policy for yourself? | E53: No, but I should get one
A54: Profile | B54: circumstances | C54: Do you have a life insurance policy for yourself? | E54: Yes, I'm all set
A55: Profile | B55: circumstances | C55: Do you have a life insurance policy for yourself? | E55: I don't know
A56: Profile | B56: circumstances | C56: Do you have an estate plan, trust, or will? | E56: No, I don't need it
A57: Profile | B57: circumstances | C57: Do you have an estate plan, trust, or will? | E57: No, but I should get one
A58: Profile | B58: circumstances | C58: Do you have an estate plan, trust, or will? | E58: Yes, I'm all set
A59: Profile | B59: circumstances | C59: Do you have an estate plan, trust, or will? | E59: I don't know
A60: Profile | B60: circumstances | C60: Do you have kids in any of these ages? | E60: Planning for kids | G60: lm-growing-your-family | I60: group-family | J60: profile-family-wantkids | M60: As of now, we can't ask this conditionally
A61: Profile | B61: circumstances | C61: Do you have kids in any of these ages? | E61: Infant and toddler
A62: Profile | B62: circumstances | C62: Do you have kids in any of these ages? | E62: Elementary age | J62: profile-family-kids-toddler
A63: Profile | B63: circumstances | C63: Do you have kids in any of these ages? | E63: Teenager | J63: profile-family-kids-teenager
A64: Profile | B64: circumstances | C64: Do you have kids in any of these ages? | E64: Adult | J64: profile-family-kids-independent
A65: Profile | C65: Potential follow up answers to "How would you describe your investment approach?" | D65: Select all that apply to you. | E65: None (I don't invest) | H65: topic-invest-none | J65: profile-invest-none
A66: Profile | C66: What best describes your investing approach? | E66: Long-term investor
A67: Profile | C67: How would you describe your investment style or experience? | E67: Short-term investor
A68: Profile | C68: Which best describes your investing style and experience? | E68: Beginner
A69: Profile | E69: Intermediate
A70: Profile | E70: Expert
A71: Profile | E71: Broadly diversified
A72: Profile | E72: Targeted investing
A73: Profile | E73: Values-based investing
A74: Profile | E74: Automated investing | F74: Contrarian investor
A75: TBD | B75: confidence & clarity | C75: I am taking advantage of all available strategies to reduce the taxes I pay.
A76: TBD | B76: confidence & clarity | C76: I am taking advantage of all available available benefits from my employer
A77: TBD | B77: confidence & clarity | C77: My financial decisions support the life I want to live and the person I want to be.
A78: TBD | B78: confidence & clarity | C78: I understand the beliefs, emotions, and biases that influence my financial decisions.
A79: TBD | B79: confidence & clarity | C79: I have a clear view of my complete financial picture – all of my assets (what I own) and my liabilities (what I owe)
A80: TBD | B80: confidence & clarity | C80: Money is a cause of stress, anxiety, or worry in my life.
A81: TBD | B81: confidence & clarity | C81: I have specific financial goals and clear strategies to achieve them.
A82: TBD | B82: confidence & clarity | C82: My debt and monthly payments are a cause of stress in my life.
A83: TBD | B83: confidence & clarity | C83: I have a clear picture of all investments and the level of risk I am taking.
A84: TBD | B84: confidence & clarity | C84: To what extent is Education Planning a concern of yours?
A85: TBD | B85: confidence & clarity | C85: I know how much money I need to save in order to achieve a financially secure retirement.
A86: TBD | B86: confidence & clarity | C86: I have the expertise and time to effectively implement all aspects of my financial plan.
A87: Profile | B87: circumstances | C87: How do you commute? | E87: Car | H87: topic-car | J87: profile-transportation-owncar | L87: parking benefit | M87: https://videos.ctfassets.net/pmoql4aw53io/4nSxcJwGTfzy1PfjnZM4FB/9c1b4067e968ad1960ea46cd7cce7eb2/onb_web_occams.mp4 | N87: occams videi
A88: Profile | B88: circumstances | C88: How do you commute? | E88: Public transit | H88: topic-budget,topic-benefits | J88: profile-transportation-public | L88: commuter benefits
A89: Profile | B89: circumstances | C89: How do you commute? | E89: I work from home
A90: Profile | B90: circumstances | C90: How do you commute? | E90: Bike | H90: topic-benefits | I90: group-self-care | J90: profile-transportation-bike
A91: Profile | B91: circumstances | C91: Do you have insurance in these? | E91: Auto | M91: I have insurance coverage in all of the categories that are important to my financial well-being (e.g. health, disability, life, and property (e.g. home, car).
A92: Profile | B92: circumstances | C92: Do you have insurance in these? | E92: Life | M92: we can use this for Wellness Score and map to existing articles
A93: Profile | B93: circumstances | C93: Do you have insurance in these? | E93: Renters
A94: Profile | B94: circumstances | C94: Do you have insurance in these? | E94: Umbrella
A95: Profile | B95: circumstances | C95: Do you have insurance in these? | E95: Disability
A96: Profile | B96: circumstances | C96: Do you have any other sources of income? | E96: side hustle
A97: Profile | B97: circumstances | C97: Do you have any other sources of income? | E97: rental property
A98: Profile | B98: circumstances | C98: Do you have any other sources of income? | E98: active investing
A99: Profile | B99: circumstances | C99: Do you have any other sources of income? | E99: other | J99: profile-investment-sidehustle
A100: Profile | B100: circumstances | C100: At what stage are you in your career? | E100: What stage are you in? | J100: profile-career-junior | M100: The answer options seem hard to interpret/distinguish; can't we infer this from their age/tenure well enough?
A101: Profile | B101: circumstances | C101: At what stage are you in your career? | E101: Do you know how to progress? | J101: profile-career-semisenior
A102: Profile | B102: circumstances | C102: At what stage are you in your career? | E102: could be a poll | J102: profile-career-senior
A103: Profile | B103: circumstances | C103: At what stage are you in your career? | J103: profile-career-howtoprogress
A104: Profile | B104: circumstances | C104: At what stage are you in your career? | J104: profile-career-manager
A105: Profile | B105: circumstances | C105: Do you have any of these types of debt? | E105: Mortgage | F105: goal-debt-management | J105: profile-debt-mortgage | M105: benefits
...

Sheet New Tag keys
A1: =_xlfn.CONCAT(_xlfn.CONCAT("Goal (", COUNTA(A2:A1000)), ")") -> Goal (6) | B1: =_xlfn.CONCAT(_xlfn.CONCAT("--deprecated Life Moment (", COUNTA(B2:B1000)), ")") -> --deprecated Life Moment (7) | C1: =_xlfn.CONCAT(_xlfn.CONCAT("Life Stage (", COUNTA(B2:B1000)), ")") -> Life Stage (7) | D1: =_xlfn.CONCAT(_xlfn.CONCAT("Content topics (",COUNTA(D2:D1000)),")") -> Content topics (67) | E1: =_xlfn.CONCAT(_xlfn.CONCAT("Content groups (",COUNTA(E2:E1000)),")") -> Content groups (18) | F1: =_xlfn.CONCAT(_xlfn.CONCAT("Profile (",COUNTA(F2:F1000)),")") -> Profile (37) | G1: =_xlfn.CONCAT(_xlfn.CONCAT("Level (",COUNTA(G2:G1000)),")") -> Level (3) | H1: =_xlfn.CONCAT(_xlfn.CONCAT("Class (",COUNTA(H2:H1000)),")") -> Class (3) | I1: =_xlfn.CONCAT(_xlfn.CONCAT("Collection (",COUNTA(I2:I1000)),")") -> Collection (0) | J1: Content Type
A2: goal-retirement | B2: lm-inheritance | C2: ls-early | D2: topic-401k | E2: group-priorities | F2: profile-family-myself | G2: level-basic | H2: class-low | J2: Calculator
A3: goal-emergency-fund | B3: lm-purposeful-learning | C3: ls-mid | D3: topic-529 | E3: group-account-types | F3: profile-family-spouse | G3: level-intermediate | H3: class-mid | J3: Benefit
A4: goal-debt-management | B4: lm-growing-your-family | C4: ls-late | D4: topic-bad-debt | E4: group-how-to-save | F4: profile-family-havekids | G4: level-advanced | H4: class-high | J4: Story
A5: goal-kids-education | D5: topic-beneficiaries | F5: profile-family-extendedfam
A6: goal-buying-a-home | B6: lm-combining-finances | D6: topic-benefit | E6: group-self-care | F6: profile-family-agingparents
A7: goal-buying-a-car | B7: lm-relocation | D7: topic-benefits | E7: group-investing-strategies | F7: profile-family-havepets
B8: lm-covid | D8: topic-brokerage | E8: group-markets | F8: profile-property-ownhome
B9: lm-none | D9: topic-budget | E9: group-career | F9: profile-property-rent
D10: topic-car | E10: group-monthly | F10: profile-property-neither
D11: topic-caregiving | E11: group-paven-app | F11: profile-priorities-budgeting
D12: topic-charity | E12: l | F12: profile-priorities-wanthome
D13: topic-credit-cards | E13: group-housing | F13: profile-priorities-collegefund
D14: topic-credit-score | E14: group-caregiving | F14: profile-priorities-estateplanning
D15: topic-crypto | E15: group-finwell | F15: profile-priorities-healthcost
D16: topic-debt | E16: group-protecting-wealth | F16: profile-priorities-investing
D17: topic-estate-planning | E17: group-family | F17: profile-priorities-lifeinsurance
D18: topic-family | E18: group-childfree | F18: profile-priorities-debtmanagement
D19: topic-financial-finesse | F19: profile-priorities-taxplanning
D20: topic-first-home | F20: profile-disability-insurance
D21: topic-free-housing | F21: profile-life-insurance
D22: topic-fsa | F22: profile-home-insurance
D23: topic-goals | F23: profile-renters-insurance
D24: topic-health | F24: profile-umbrella-insurance
D25: topic-hsa | F25: profile-will
D26: topic-income | F26: profile-trust
D27: topic-industries | F27: profile-guardianship
D28: topic-inflation | F28: profile-beneficiaries
D29: topic-inheritance | F29: profile-goal-progress-never
D30: topic-insurance | F30: profile-goal-progress-yearly
... D38: topic-partner | F38: profile-invest-none
D39: topic-pets
D40: topic-relocation
D41: topic-renting
D42: topic-resilience
D43: topic-retirement
D44: topic-roth-ira
D45: topic-rsus
D46: topic-savviness
D47: topic-self-care
D48: topic-side-hustle
D49: topic-simulator
D50: topic-skills
... D62: topic-childfree
D78: topic-spending | E78: group-polls
D79: topic-lifestyles | E79: group-homeownership
D80: topic-sustainability
D81: topic-mentalhealth
D82: topic-buyhome
D83: topic-buycar

Sheet Tags 2025
A1: date | B1: id | C1: title | D1: goal_tags | E1: life_moment_tags | F1: life_stage_tags | G1: content_tags | H1: group_tags | I1: Profile Builder | J1: Link to V1 | K1: Link to V2 | L1: class_tags | M1: Audit notes | N1: Tenant | O1: Link | P1: Jolene Notes
A2: 2021 Q3 | B2: TT_1.4 | C2: Ways to use your pay raise | E2: lm-purposeful-learning | F2: ls-early ls-mid ls-late | G2: topic-income, topic-savviness | H2: group-how-to-save | I2: profile-family-myself profile-priorities-budgeting | L2: class-low | M2: class-mid | N2: general/meta | O2: https://paven.io/content/article/4cLNM7gf8dHQxcynhtkuDG | P2: Not much meat there. Mentions updating budget but no link.
A3: 2021 Q3 | B3: EMF_1.1 | C3: Do I need an emergency fund? | D3: goal-emergency-fund | E3: lm-purposeful-learning | F3: ls-early ls-mid ls-late | G3: topic-resilience | H3: group-priorities, group-how-to-save | I3: profile-priorities-budgeting | J3: https://www.figma.com/design/UOXktKMNWVxBSuZJhNGdyu/Goals?node-id=3496-10081&t=d6MHhwFJ4Ajl1iXH-1 | L3: class-low | O3: https://paven.io/content/article/3XIA1q18lV1NZXHVhmUVfV | P3: Links externally to articles, some of those links are broken/missing
A4: 2021 Q4 | B4: EMF_1.2 | C4: Saving for the unknown | D4: goal-emergency-fund | E4: lm-purposeful-learning | F4: ls-early ls-mid ls-late | G4: topic-resilience | H4: group-how-to-save | I4: profile-priorities-budgeting | J4: https://www.figma.com/design/UOXktKMNWVxBSuZJhNGdyu/Goals?node-id=3496-10082&t=d6MHhwFJ4Ajl1iXH-1 | L4: class-low | O4: https://paven.io/content/article/10BCj5GYLPT2pnrmRa8G01 | P4: Seems to have issues with 1 of the graphics
A5: 2021 Q4 | B5: SFC_1.8 | C5: Get help from a College Coach | D5: goal-kids-education | G5: topic-kids-education, topic-financial-coach | I5: profile-family-havekids | J5: https://www.figma.com/design/UOXktKMNWVxBSuZJhNGdyu/Goals?node-id=3500-67995&t=d6MHhwFJ4Ajl1iXH-1 | L5: archived
A6: 2021 Q4 | B6: RET_1.10 | C6: The basics of Meta's 401(k) plan | D6: goal-retirement | F6: ls-early ls-mid ls-late | G6: topic-retirement, topic-401k | H6: group-account-types | I6: profile-priorities-investing | J6: https://www.figma.com/design/UOXktKMNWVxBSuZJhNGdyu/Goals?node-id=3506-15659&t=d6MHhwFJ4Ajl1iXH-1 | L6: class-mid | O6: https://paven.io/benefits/article/5xcJNCiEQbb4PJHJ6glj3c | P6: Mentions of 2022 2023
A7: 2021 Q4 | B7: MM_1.7 | C7: College coaching from Bright Horizons | D7: goal-kids-education | G7: group-family, topic-benefits | I7: profile-family-havekids profile-priorities-collegefund | L7: archived
A8: 2021 Q4 | B8: DEB_1.6 | C8: Get support with Lyra | D8: goal-debt-management | F8: ls-early ls-mid ls-late | G8: topic-lyra | H8: group-how-to-save | I8: profile-priorities-healthcost | J8: https://www.figma.com/design/UOXktKMNWVxBSuZJhNGdyu/Goals?node-id=3508-49770&t=d6MHhwFJ4Ajl1iXH-1 | L8: class-mid
A9: 2021 Q4 | B9: LM_RELO_1.1 | C9: Relocation 101 | E9: lm-relocation | F9: ls-early ls-mid ls-late | G9: topic-relocation | H9: group-priorities | I9: profile-priorities-debtmanagement | J9: https://www.figma.com/design/kkMh7aGZkJopf7n5lbrrpX/Life-Moments?node-id=2565-20757&t=scW7PhQJA030oT78-1 | L9: class-low | M9: Still relevant? | O9: https://paven.io/content/article/4EDqrnZqjMVLUmpzRwSjk2
A10: 2021 Q4 | B10: LM_RELO_1.2 | C10: Buying a car when relocating | D10: goal-buying-a-car | E10: lm-relocation | F10: ls-early ls-mid ls-late | G10: topic-car | H10: group-priorities | I10: profile-priorities-debtmanagement | J10: https://www.figma.com/design/kkMh7aGZkJopf7n5lbrrpX/Life-Moments?node-id=2565-23387&t=scW7PhQJA030oT78-1 | L10: class-low | M10: Still relevant? | O10: https://paven.io/content/article/7oATLbHlAL221cMeVUAoy6
A11: 2021 Q4 | B11: LM_RELO_1.3 | C11: Save for emergencies or send money home? | D11: goal-emergency-fund, goal-buying-a-home | E11: lm-growing-your-family, lm-relocation | F11: ls-early ls-mid ls-late | G11: topic-resilience | H11: group-priorities | I11: profile-goal-progress-never profile-goal-progress-yearly profile-goal-progress-quarterly profile-goal-progress-monthly profile-goal-progress-weekly profile-goal-progress-daily | J11: https://www.figma.com/design/kkMh7aGZkJopf7n5lbrrpX/Life-Moments?node-id=2565-23389&t=scW7PhQJA030oT78-1 | L11: class-low | M11: Still relevant? | O11: https://paven.io/content/article/7MiY8sNHiCZuc076FEazOe
A12: 2021 Q4 | B12: LM_RELO_1.5 | C12: Save for retirement or send money home? | D12: goal-retirement, goal-buying-a-home | E12: lm-relocation | G12: topic-resilience | H12: group-priorities | I12: profile-goal-progress-never profile-goal-progress-yearly profile-goal-progress-quarterly profile-goal-progress-monthly profile-goal-progress-weekly profile-goal-progress-daily | J12: https://www.figma.com/design/kkMh7aGZkJopf7n5lbrrpX/Life-Moments?node-id=2565-23390&t=scW7PhQJA030oT78-1 | L12: class-low | M12: Still relevant? | O12: https://paven.io/content/article/6BSnt3S9Zwu74QHDX1PhsS
A13: 2021 Q4 | B13: EMF_1.3 | C13: Where to stash emergency funds | D13: goal-emergency-fund | G13: topic-resilience | H13: group-account-types | I13: profile-priorities-debtmanagement profile-priorities-budgeting | J13: https://www.figma.com/design/UOXktKMNWVxBSuZJhNGdyu/Goals?node-id=3496-10080&t=d6MHhwFJ4Ajl1iXH-1 | L13: class-mid | O13: https://paven.io/content/article/2vcmDPcrP6hJEuqJ6Q086E
A14: 2021 Q4 | B14: EMF_1.5 | C14: Setting up automatic transfers | D14: goal-emergency-fund | G14: topic-emergency-fund, topic-automatic-transfers | H14: group-how-to-save | I14: profile-priorities-debtmanagement profile-priorities-budgeting | J14: https://www.figma.com/design/UOXktKMNWVxBSuZJhNGdyu/Goals?node-id=3496-6025&t=d6MHhwFJ4Ajl1iXH-1 | L14: class-low | N14: Old/Needs to be rewritten | O14: https://paven.io/content/article/5lKy8OxVNCgejG7EfH3fKD
A15: 2021 Q4 | B15: EMF_1.6 | C15: How to boost emergency funds | D15: goal-emergency-fund | G15: topic-resilience | H15: group-how-to-save | I15: profile-priorities-debtmanagement profile-priorities-budgeting | J15: https://www.figma.com/design/UOXktKMNWVxBSuZJhNGdyu/Goals?node-id=3496-5926&t=d6MHhwFJ4Ajl1iXH-1 | L15: class-low | N15: Can be refreshed | O15: https://paven.io/content/article/7qXkRnZzobZjwtH2EMEerV
A16: 2021 Q4 | B16: SFC_1.1 | C16: 3 reasons to start saving now | D16: goal-kids-education | G16: group-family | H16: group-priorities | I16: profile-priorities-debtmanagement profile-priorities-budgeting | J16: https://www.figma.com/design/UOXktKMNWVxBSuZJhNGdyu/Goals?node-id=3500-67988&t=d6MHhwFJ4Ajl1iXH-1 | L16: class-low | N16: Good | O16: https://paven.io/content/article/2YEbx95wNuqCh5IS2Z6Mi9
A17: 2021 Q4 | B17: SFC_1.3 | C17: Education account types | D17: goal-kids-education | G17: group-family | H17: group-account-types | I17: profile-family-havekids profile-priorities-collegefund | J17: https://www.figma.com/design/UOXktKMNWVxBSuZJhNGdyu/Goals?node-id=3500-67990&t=d6MHhwFJ4Ajl1iXH-1 | L17: class-low | O17: https://paven.io/content/article/6Y95jlQhFRWdOUFnt4Egm
A18: 2021 Q4 | B18: SFC_1.4 | C18: The 529 plan, explained | D18: goal-kids-education | G18: topic-529 | H18: group-account-types, group-how-to-save | I18: profile-family-havekids profile-priorities-collegefund | J18: https://www.figma.com/design/UOXktKMNWVxBSuZJhNGdyu/Goals?node-id=3500-67991&t=d6MHhwFJ4Ajl1iXH-1 | L18: class-low | O18: https://paven.io/content/article/5QCbiymJdeZtNQV75taLwk
A19: 2021 Q4 | B19: SFC_1.5 | C19: Using a Roth IRA to save | D19: goal-kids-education | G19: topic-roth-ira, group-how-to-save | H19: group-account-types | I19: profile-priorities-investing profile-invest-beginner profile-invest-intermediate profile-invest-advanced profile-invest-none | J19: https://www.figma.com/design/UOXktKMNWVxBSuZJhNGdyu/Goals?node-id=3500-67992&t=d6MHhwFJ4Ajl1iXH-1 | L19: class-low | O19: https://paven.io/content/article/CZcZvvvFjtJcHiHM3DzN8
A20: 2021 Q4 | B20: SFC_1.6 | C20: Using a brokerage account to save | G20: topic-brokerage | H20: group-account-types | I20: profile-priorities-investing profile-invest-beginner profile-invest-intermediate profile-invest-advanced profile-invest-none | J20: https://www.figma.com/design/UOXktKMNWVxBSuZJhNGdyu/Goals?node-id=3500-67993&t=d6MHhwFJ4Ajl1iXH-1 | L20: class-low | O20: https://paven.io/content/article/7rKjk2k5RiPMLiKRcoXrZ1
A21: 2021 Q4 | B21: SFC_1.7 | C21: Other ways to save for education | D21: goal-kids-education | G21: group-family | H21: group-how-to-save | I21: profile-family-havekids profile-priorities-collegefund | J21: https://www.figma.com/design/UOXktKMNWVxBSuZJhNGdyu/Goals?node-id=3500-67994&t=d6MHhwFJ4Ajl1iXH-1 | L21: class-low | O21: https://paven.io/content/article/6T84VV9e9fDftdKikDRksz
A22: 2021 Q4 | B22: DEB_1.1 | C22: Good debt vs bad debt | D22: goal-debt-management | G22: topic-bad-debt, group-how-to-save | H22: group-priorities | I22: profile-priorities-debtmanagement profile-priorities-budgeting | J22: https://www.figma.com/design/UOXktKMNWVxBSuZJhNGdyu/Goals?node-id=3508-49764&t=d6MHhwFJ4Ajl1iXH-1 | L22: class-mid | O22: https://paven.io/content/article/2ActWmf1Hdnh80tgVgUiJ3
A23: 2021 Q4 | B23: DEB_1.2 | C23: Dealing with student loan debt | D23: goal-debt-management | G23: topic-student-loans | H23: group-how-to-save | I23: profile-family-havekids profile-priorities-collegefund profile-priorities-debtmanagement | J23: https://www.figma.com/design/UOXktKMNWVxBSuZJhNGdyu/Goals?node-id=3508-49765&t=d6MHhwFJ4Ajl1iXH-1 | L23: class-low | O23: https://paven.io/content/article/6Eee9pQ3rSkCdLJnUBahVT
A24: 2021 Q4 | B24: DEB_1.3 | C24: How credit card debt works | D24: goal-debt-management | G24: topic-credit-cards, topic-resilience | H24: group-how-to-save | I24: profile-priorities-debtmanagement | J24: https://www.figma.com/design/UOXktKMNWVxBSuZJhNGdyu/Goals?node-id=3508-49766&t=d6MHhwFJ4Ajl1iXH-1 | L24: class-low | O24: https://paven.io/content/article/5hayL3vE1ypoDE8ELKcbtJ
A25: 2021 Q4 | B25: DEB_1.7 | C25: Credit scores 101 | D25: goal-debt-management | G25: topic-credit-score, topic-resilience | I25: profile-priorities-debtmanagement | J25: https://www.figma.com/design/UOXktKMNWVxBSuZJhNGdyu/Goals?node-id=3508-49771&t=d6MHhwFJ4Ajl1iXH-1 | L25: class-low | O25: https://paven.io/content/article/1NZMCPBnYrfE3v0M9fSXt4
A26: 2021 Q4 | B26: DEB_1.8 | C26: Track your debt payments | D26: goal-debt-management | G26: topic-bad-debt | H26: group-how-to-save | I26: profile-priorities-debtmanagement | J26: https://www.figma.com/design/UOXktKMNWVxBSuZJhNGdyu/Goals?node-id=3508-51036&t=d6MHhwFJ4Ajl1iXH-1 | L26: class-low | O26: https://paven.io/content/article/btv3P3YdkxNf0zqcwEAH4
A27: 2021 Q4 | B27: DEB_1.4 | C27: Tips to cut credit card debt | D27: goal-debt-management | G27: topic-credit-cards, topic-savviness | H27: group-how-to-save | I27: profile-priorities-debtmanagement | J27: https://www.figma.com/design/UOXktKMNWVxBSuZJhNGdyu/Goals?node-id=3508-49767&t=d6MHhwFJ4Ajl1iXH-1 | L27: class-mid | O27: https://paven.io/content/article/31poVSYMQMCbeM2FQofIRi
A28: 2021 Q4 | B28: RET_1.1 | C28: Retiring on your own terms | D28: goal-retirement | G28: topic-retirement | H28: group-priorities | I28: profile-family-myself profile-priorities-debtmanagement | J28: https://www.figma.com/design/UOXktKMNWVxBSuZJhNGdyu/Goals?node-id=3505-71716&t=d6MHhwFJ4Ajl1iXH-1 | L28: class-low | O28: https://paven.io/content/article/7vvkK5XEvXpA8tIDWNQlnH
A29: 2021 Q4 | B29: RET_1.2 | C29: Common barriers to saving | D29: goal-retirement | G29: topic-retirement, topic-401k | H29: group-how-to-save | I29: profile-goal-progress-never profile-goal-progress-yearly profile-goal-progress-quarterly profile-goal-progress-monthly profile-goal-progress-weekly profile-goal-progress-daily profile-priorities-debtmanagement | J29: https://www.figma.com/design/UOXktKMNWVxBSuZJhNGdyu/Goals?node-id=3506-7718&t=d6MHhwFJ4Ajl1iXH-1 | L29: class-low | O29: https://paven.io/content/article/1uEkmd8hDB1fPrHMXux21T
A30: 2021 Q4 | B30: RET_1.3 | C30: Define your target number | D30: goal-retirement | G30: topic-retirement, topic-401k | H30: group-priorities | I30: profile-goal-progress-never profile-goal-progress-yearly profile-goal-progress-quarterly profile-goal-progress-monthly profile-goal-progress-weekly profile-goal-progress-daily profile-priorities-debtmanagement | J30: https://www.figma.com/design/UOXktKMNWVxBSuZJhNGdyu/Goals?node-id=3506-15144&t=d6MHhwFJ4Ajl1iXH-1 | L30: class-low | O30: https://paven.io/content/article/7cSZtBYtkbyVT6P2o43ibs
A31: 2021 Q4 | B31: RET_1.4 | C31: Add your post-retirement work | D31: goal-retirement | G31: topic-retirement | H31: group-priorities | I31: profile-goal-progress-never profile-goal-progress-yearly profile-goal-progress-quarterly profile-goal-progress-monthly profile-goal-progress-weekly profile-goal-progress-daily profile-priorities-debtmanagement | J31: https://www.figma.com/design/UOXktKMNWVxBSuZJhNGdyu/Goals?node-id=3506-15653&t=d6MHhwFJ4Ajl1iXH-1 | L31: class-low | O31: https://paven.io/content/article/lwALm8GoRRB2UNy66fjhy
A32: 2021 Q4 | B32: RET_1.5 | C32: 401(k) basics | D32: goal-retirement | G32: topic-401k | H32: group-account-types | I32: profile-priorities-investing | J32: https://www.figma.com/design/UOXktKMNWVxBSuZJhNGdyu/Goals?node-id=3506-15654&t=d6MHhwFJ4Ajl1iXH-1 | L32: class-mid
A33: 2021 Q4 | B33: RET_1.8 | C33: Is a 401(k) loan a good option? | D33: goal-retirement | G33: topic-401k, topic-retirement | H33: group-account-types | I33: profile-priorities-investing | J33: https://www.figma.com/design/UOXktKMNWVxBSuZJhNGdyu/Goals?node-id=3506-15657&t=d6MHhwFJ4Ajl1iXH-1 | L33: class-low | O33: https://paven.io/content/article/1vdq8TQD1jqGJJvX3Wn53o
A34: 2021 Q4 | B34: LM_COM_1.4 | C34: Travel or save for emergencies? | D34: goal-emergency-fund | E34: lm-combining-finances | G34: topic-resilience | H34: group-how-to-save | I34: profile-priorities-debtmanagement profile-priorities-budgeting | J34: https://www.figma.com/design/kkMh7aGZkJopf7n5lbrrpX/Life-Moments?node-id=2565-19454&t=scW7PhQJA030oT78-1 | L34: class-low | O34: https://paven.io/content/article/4EdrGH95P0rcBrdli5jKXB
A35: 2021 Q4 | B35: LM_COM_1.5 | C35: Pay off debt or buy a home? | D35: goal-debt-management, goal-buying-a-home | E35: lm-combining-finances | G35: topic-resilience | H35: group-priorities | I35: profile-priorities-debtmanagement profile-priorities-budgeting | J35: https://www.figma.com/design/kkMh7aGZkJopf7n5lbrrpX/Life-Moments?node-id=2565-19455&t=scW7PhQJA030oT78-1 | L35: class-low | O35: https://paven.io/content/article/6JPHUAfF9TrK1IfGnXOu0i
A36: 2021 Q4 | B36: BAH_1.1 | C36: Ease your home buying concerns | D36: goal-buying-a-home | G36: topic-housing, topic-rent | H36: group-priorities | I36: profile-priorities-wanthome | L36: class-low | O36: https://paven.io/content/article/30CmxhE9d1pcdGvGaYSuId
A37: 2021 Q4 | B37: TF_1.1 | C37: Travel today and save for tomorrow | D37: goal-debt-management | G37: topic-travel | H37: group-priorities | I37: profile-priorities-debtmanagement profile-priorities-budgeting | J37: https://www.figma.com/design/UOXktKMNWVxBSuZJhNGdyu/Goals?node-id=3498-39610&t=d6MHhwFJ4Ajl1iXH-1 | L37: class-low | O37: https://paven.io/content/article/3ZweQAOsrsqgm28SCZF09Q
A38: 2021 Q4 | B38: TF_1.2 | C38: What kind of traveler are you? | G38: topic-travel | H38: group-priorities | I38: profile-priorities-debtmanagement profile-priorities-budgeting | J38: https://www.figma.com/design/UOXktKMNWVxBSuZJhNGdyu/Goals?node-id=3498-39611&t=d6MHhwFJ4Ajl1iXH-1 | L38: class-low | O38: https://paven.io/content/article/5YkoPnRVpjBLBo3WxrT37z
A39: 2021 Q4 | B39: TF_1.3 | C39: Travel fund strategies | D39: goal-debt-management | G39: topic-travel | H39: group-how-to-save | I39: profile-priorities-debtmanagement profile-priorities-budgeting | J39: https://www.figma.com/design/UOXktKMNWVxBSuZJhNGdyu/Goals?node-id=3498-39612&t=d6MHhwFJ4Ajl1iXH-1 | L39: class-low | O39: https://paven.io/content/article/7jBOX3g5w5ONNw06nvapin
A40: 2021 Q4 | B40: TF_1.4 | C40: Find like-minded travel companions | G40: topic-travel | H40: group-self-care | I40: profile-priorities-debtmanagement profile-priorities-budgeting | J40: https://www.figma.com/design/UOXktKMNWVxBSuZJhNGdyu/Goals?node-id=3498-39613&t=d6MHhwFJ4Ajl1iXH-1 | L40: class-low | O40: https://paven.io/content/article/h1TiRXpgSLIIVAiNuVqjF
A41: 2021 Q4 | B41: TF_1.5 | C41: Ways to save on trips | D41: goal-debt-management | G41: topic-travel | H41: group-how-to-save | I41: profile-priorities-debtmanagement profile-priorities-budgeting | J41: https://www.figma.com/design/UOXktKMNWVxBSuZJhNGdyu/Goals?node-id=3498-39614&t=d6MHhwFJ4Ajl1iXH-1 | L41: class-low | O41: https://paven.io/content/article/1DmCiLW9zxoFOpqpA2J2Wd
A42: 2021 Q4 | B42: GYF_1.1 | C42: Align your family's financial needs | D42: goal-debt-management, goal-buying-a-home | E42: lm-growing-your-family, lm-combining-finances | G42: group-family | H42: group-priorities | I42: profile-priorities-debtmanagement profile-priorities-budgeting | J42: https://www.figma.com/design/kkMh7aGZkJopf7n5lbrrpX/Life-Moments?node-id=2562-6324&t=scW7PhQJA030oT78-1 | L42: class-low | O42: https://paven.io/content/article/7xetvRhKmHMTYoRmZfgTa9
A43: 2021 Q4 | B43: BAH_1.3 | C43: Down payments: The basics | D43: goal-buying-a-home | G43: topic-loans, topic-housing | H43: group-priorities | I43: profile-priorities-wanthome | J43: https://www.figma.com/design/UOXktKMNWVxBSuZJhNGdyu/Goals?node-id=3540-44300&t=d6MHhwFJ4Ajl1iXH-1 | L43: class-low | O43: https://paven.io/content/article/4vG7iuIiWd1VG5n01X2afX
A44: 2021 Q4 | B44: GYF_1.9 | C44: Buying a home for your family | D44: goal-buying-a-home | E44: lm-growing-your-family, lm-combining-finances | G44: group-family, topic-housing | H44: group-priorities | I44: profile-priorities-wanthome | J44: https://www.figma.com/design/kkMh7aGZkJopf7n5lbrrpX/Life-Moments?node-id=2562-6333&t=scW7PhQJA030oT78-1 | L44: class-low | O44: https://paven.io/content/article/7uhXBF090dFidOiHYMXhU7
A45: 2022 Q1 | B45: DEB_1.5 | C45: Refinance your student loans with Sofi & Earnest | D45: goal-debt-management | G45: topic-debt, topic-student-loans, topic-refinancing | H45: group-how-to-save | I45: profile-priorities-debtmanagement profile-priorities-budgeting | J45: https://www.figma.com/design/UOXktKMNWVxBSuZJhNGdyu/Goals?node-id=3508-49768&t=d6MHhwFJ4Ajl1iXH-1 | L45: class-low | O45: https://paven.io/benefits/article/3iNseJtkBv6m5HNQV8QjDC
A46: 2022 Q1 | B46: TF_1.8 | C46: Personal travel & Meta benefits | G46: topic-travel, topic-benefits | H46: group-self-care | I46: profile-priorities-debtmanagement profile-priorities-budgeting | J46: https://www.figma.com/design/UOXktKMNWVxBSuZJhNGdyu/Goals?node-id=3498-33447&t=d6MHhwFJ4Ajl1iXH-1 | L46: class-low | O46: https://paven.io/content/article/5ec1eOLS5EBKWvZpMuyQmu
A47: 2022 Q1 | B47: ES_1.4 | C47: How can Meta support your growth? | E47: lm-purposeful-learning | G47: topic-benefits | H47: group-career | I47: profile-family-myself profile-priorities-healthcost | K47: https://www.figma.com/design/i47pYiJ10vqlvx0co3h46m/Q4-2022---Q1-2023-Content-Articles-(batch-16-23)?node-id=456-39144&t=V1quavg1MmDh9NVO-1 | L47: class-low | O47: https://paven.io/content/article/2CIso7UC3q3Kah6N4Wqk78
A48: 2022 Q1 | B48: HOME_1.4 | C48: Financial Finesse: Connect with a coach | D48: goal-debt-management | G48: topic-financial-coach | H48: group-benefits | I48: profile-priorities-investing profile-priorities-debtmanagement profile-priorities-taxplanning | L48: class-high | O48: https://paven.io/benefits/article/1gd9ZmQkYFEtWHRWxNeOAb
A49: 2022 Q1 | B49: RET_1.6 | C49: Your Fidelity 401(k) options | D49: goal-retirement | G49: topic-401k, topic-benefits | H49: group-benefits | I49: profile-priorities-investing | K49: https://www.figma.com/design/i47pYiJ10vqlvx0co3h46m/Q4-2022---Q1-2023-Content-Articles-(batch-16-23)?node-id=461-34818&t=V1quavg1MmDh9NVO-1 | L49: class-mid | O49: https://paven.io/benefits/article/37K6qv3YXJWe5lc4geHKqv
A50: 2022 Q1 | B50: SMINV_1.1 | C50: What is smart investing? | G50: topic-savviness | H50: group-investing-strategies | I50: profile-priorities-investing | K50: https://www.figma.com/design/i47pYiJ10vqlvx0co3h46m/Q4-2022---Q1-2023-Content-Articles-(batch-16-23)?node-id=364-20934&t=V1quavg1MmDh9NVO-1 | L50: class-low | O50: https://paven.io/content/article/6xmHo7bAgJ4twMxWcbmCw3
A51: 2022 Q1 | B51: SMINV_1.2 | C51: Why smart investing? | G51: topic-smart-investing | H51: group-investing-strategies | I51: profile-priorities-investing | K51: https://www.figma.com/design/i47pYiJ10vqlvx0co3h46m/Q4-2022---Q1-2023-Content-Articles-(batch-16-23)?node-id=364-20936&t=V1quavg1MmDh9NVO-1 | L51: class-low | O51: https://paven.io/content/article/6xmHo7bAgJ4twMxWcbmCw3
A52: 2022 Q1 | B52: SMINV_1.3 | C52: Choosing to be a smart investor | G52: topic-savviness, topic-investing | H52: group-investing-strategies | I52: profile-priorities-investing | K52: https://www.figma.com/design/i47pYiJ10vqlvx0co3h46m/Q4-2022---Q1-2023-Content-Articles-(batch-16-23)?node-id=364-20937&t=V1quavg1MmDh9NVO-1 | L52: class-low | O52: https://paven.io/content/article/6A6PR0ME903Lb3OPehOwwW
A53: 2022 Q1 | B53: TF_1.6 | C53: Sticking to a trip budget | D53: goal-debt-management | G53: topic-travel | H53: group-how-to-save | I53: profile-priorities-debtmanagement profile-priorities-budgeting | J53: https://www.figma.com/design/UOXktKMNWVxBSuZJhNGdyu/Goals?node-id=3498-39615&t=d6MHhwFJ4Ajl1iXH-1 | L53: class-low | O53: https://paven.io/content/article/20OmH46TN5N7bpl5DNm6qO
A54: 2022 Q1 | B54: TF_1.7 | C54: Saving for regular trips | G54: topic-travel | H54: group-how-to-save | I54: profile-priorities-debtmanagement profile-priorities-budgeting | J54: https://www.figma.com/design/UOXktKMNWVxBSuZJhNGdyu/Goals?node-id=3498-37136&t=d6MHhwFJ4Ajl1iXH-1 | L54: class-low | O54: https://paven.io/content/article/1PVeIS7NGs54PPOaefT47D
A55: 2022 Q1 | B55: SMINV_1.4 | C55: Stocks and bonds: the basics | G55: topic-stocks-bonds, topic-investing | H55: group-investing-strategies | I55: profile-priorities-investing profile-invest-beginner profile-invest-intermediate profile-invest-advanced profile-invest-none | K55: https://www.figma.com/design/i47pYiJ10vqlvx0co3h46m/Q4-2022---Q1-2023-Content-Articles-(batch-16-23)?node-id=364-20941&t=V1quavg1MmDh9NVO-1 | L55: class-mid | O55: https://paven.io/content/article/3S7nyY4lreozOyIPFJSNwA
A56: 2022 Q1 | B56: SMINV_1.5 | C56: Smart investing strategies | G56: topic-savviness, topic-investing | H56: group-investing-strategies | I56: profile-priorities-investing profile-invest-beginner profile-invest-intermediate profile-invest-advanced profile-invest-none | K56: https://www.figma.com/design/i47pYiJ10vqlvx0co3h46m/Q4-2022---Q1-2023-Content-Articles-(batch-16-23)?node-id=364-20940&t=V1quavg1MmDh9NVO-1 | L56: class-low | O56: https://paven.io/content/article/74omo1S558IxKBOvxa3FOF
A57: 2022 Q1 | B57: SMINV_1.7 | C57: Emerging and evolving industries | G57: topic-industries | H57: group-investing-strategies | I57: profile-priorities-investing profile-invest-beginner profile-invest-intermediate profile-invest-advanced profile-invest-none | K57: https://www.figma.com/design/i47pYiJ10vqlvx0co3h46m/Q4-2022---Q1-2023-Content-Articles-(batch-16-23)?node-id=364-20938&t=V1quavg1MmDh9NVO-1 | L57: class-low | O57: https://paven.io/content/article/5U5ooQfYzyhvW8tjsb21zd
A58: 2022 Q1 | B58: SMINV_1.6 | C58: Map your smart investor route | G58: topic-savviness | H58: group-investing-strategies | I58: profile-priorities-investing profile-invest-beginner profile-invest-intermediate profile-invest-advanced profile-invest-none | K58: https://www.figma.com/design/i47pYiJ10vqlvx0co3h46m/Q4-2022---Q1-2023-Content-Articles-(batch-16-23)?node-id=364-20939&t=V1quavg1MmDh9NVO-1 | L58: class-low | O58: https://paven.io/content/article/5wxMC862ZgudsL0ci1yDQV
A59: 2022 Q1 | B59: GYF_1.10 | C59: Setting your kid up for future success | D59: goal-kids-education | E59: lm-growing-your-family, lm-combining-finances | G59: group-family, topic-529 | H59: group-priorities | I59: profile-family-havekids profile-priorities-collegefund | L59: class-low | O59: https://paven.io/content/article/3hojfRCz5EwIG4gmFoyjf7
A60: 2022 Q1 | B60: ES_1.1 | C60: Enhance your skills to enhance your career | E60: lm-purposeful-learning | G60: topic-career | H60: group-career | I60: profile-goal-progress-never profile-goal-progress-yearly profile-goal-progress-quarterly profile-goal-progress-monthly profile-goal-progress-weekly profile-goal-progress-daily | K60: https://www.figma.com/design/i47pYiJ10vqlvx0co3h46m/Q4-2022---Q1-2023-Content-Articles-(batch-16-23)?node-id=456-39146&t=V1quavg1MmDh9NVO-1 | L60: class-low | O60: https://paven.io/content/article/1yTRmV6XUnKbF5FnFtGkG5
A61: 2022 Q1 | B61: ES_1.2 | C61: How do I fulfill my financial and career goals? | G61: topic-career | H61: group-career | I61: profile-goal-progress-never profile-goal-progress-yearly profile-goal-progress-quarterly profile-goal-progress-monthly profile-goal-progress-weekly profile-goal-progress-daily | K61: https://www.figma.com/design/i47pYiJ10vqlvx0co3h46m/Q4-2022---Q1-2023-Content-Articles-(batch-16-23)?node-id=456-39145&t=V1quavg1MmDh9NVO-1 | L61: class-low | O61: https://paven.io/content/article/52rmUS8u4AdY94focFUpI9
A62: 2022 Q1 | B62: ES_1.3 | C62: Common learning paths to enhance skills | G62: topic-career | H62: group-career | I62: profile-goal-progress-never profile-goal-progress-yearly profile-goal-progress-quarterly profile-goal-progress-monthly profile-goal-progress-weekly profile-goal-progress-daily | K62: https://www.figma.com/design/i47pYiJ10vqlvx0co3h46m/Q4-2022---Q1-2023-Content-Articles-(batch-16-23)?node-id=456-39143&t=V1quavg1MmDh9NVO-1 | L62: class-low | O62: https://paven.io/content/article/66VCctIqO7bnPrHKJUwcpF
A63: 2022 Q2 | B63: The power of compounding interest | C63: The power of compounding interest | G63: topic-retirement, topic-budget, topic-compounding, topic-simulator | H63: group-investing-strategies | I63: profile-priorities-investing profile-invest-beginner profile-invest-intermediate profile-invest-advanced profile-invest-none | L63: class-high | M63: (simulator) | O63: https://paven.io/simulator/article/7MJHtQVMn3oHeuyZYZ7LrB
A64: 2022 Q2 | B64: Tax Refund_SIMULATOR | C64: How to get the most out of your tax refund | E64: lm-purposeful-learning | G64: topic-taxes, topic-simulator | H64: group-investing-strategies | I64: profile-priorities-taxplanning | L64: class-high | M64: (simulator) | O64: https://paven.io/simulator/article/3BMy1Sz9edk5R9STChJbrl
A65: 2022 Q2 | B65: SMINV_1.18 | C65: Can you stay in the market? | G65: topic-savviness | H65: group-markets | I65: profile-priorities-investing profile-invest-beginner profile-invest-intermediate profile-invest-advanced profile-invest-none | K65: https://www.figma.com/design/i47pYiJ10vqlvx0co3h46m/Q4-2022---Q1-2023-Content-Articles-(batch-16-23)?node-id=374-36558&t=V1quavg1MmDh9NVO-1 | L65: class-low | M65: A lot of these Smart Investing pieces reuse language/assets. Need to be consolidated. | O65: https://paven.io/content/article/4NN8LJ6HdLbD3FhR6xH9hd
A66: 2022 Q2 | B66: SMINV_1.9 | C66: Is now a good time to invest? | G66: topic-savviness, topic-smart-investing | H66: group-markets | I66: profile-priorities-investing profile-invest-beginner profile-invest-intermediate profile-invest-advanced profile-invest-none | K66: https://www.figma.com/design/i47pYiJ10vqlvx0co3h46m/Q4-2022---Q1-2023-Content-Articles-(batch-16-23)?node-id=377-41082&t=V1quavg1MmDh9NVO-1 | L66: class-low | O66: https://paven.io/content/article/6c21mg94YY9xqv3xNRCF6b
A67: 2022 Q2 | B67: SMINV_1.8 | C67: Why should you invest? | G67: topic-savviness, topic-smart-investing | H67: group-investing-strategies | I67: profile-priorities-investing profile-invest-beginner profile-invest-intermediate profile-invest-advanced profile-invest-none | K67: https://www.figma.com/design/i47pYiJ10vqlvx0co3h46m/Q4-2022---Q1-2023-Content-Articles-(batch-16-23)?node-id=377-41081&t=V1quavg1MmDh9NVO-1 | L67: class-mid | O67: https://paven.io/content/article/3q3tsXFp5W4eSMo4yFGXJh
A68: 2022 Q2 | B68: SMINV_1.10 | C68: Can you time the market? | G68: topic-smart-investing, topic-savviness | H68: group-markets | I68: profile-priorities-investing profile-invest-beginner profile-invest-intermediate profile-invest-advanced profile-invest-none | K68: https://www.figma.com/design/i47pYiJ10vqlvx0co3h46m/Q4-2022---Q1-2023-Content-Articles-(batch-16-23)?node-id=377-41083&t=V1quavg1MmDh9NVO-1 | L68: class-low | O68: https://paven.io/content/article/10hEZDS9HPFQI88Dy49DTh
A69: 2022 Q2 | B69: SMINV_1.11 | C69: Market volatility: How to navigate | G69: topic-volatility, topic-savviness | H69: group-markets | I69: profile-priorities-investing profile-invest-beginner profile-invest-intermediate profile-invest-advanced profile-invest-none | K69: https://www.figma.com/design/i47pYiJ10vqlvx0co3h46m/Q4-2022---Q1-2023-Content-Articles-(batch-16-23)?node-id=377-41084&t=V1quavg1MmDh9NVO-1 | L69: class-low | O69: https://paven.io/content/article/4AVBAIJEUPBkrXOgCyHhGC
A70: 2022 Q2 | B70: SMINV_1.12 | C70: How to make money in a downturn market | G70: topic-volatility, topic-savviness | H70: group-markets | I70: profile-priorities-investing profile-invest-beginner profile-invest-intermediate profile-invest-advanced profile-invest-none | L70: class-low | O70: https://paven.io/content/article/27qsF992ZH4QiAcAhG2dOB
A71: 2022 Q2 | B71: SH_1.5 | C71: What are the rewards of a side hustle? | D71: goal-retirement | G71: topic-side-hustle, topic-income | I71: profile-priorities-debtmanagement | K71: https://www.figma.com/design/i47pYiJ10vqlvx0co3h46m/Q4-2022---Q1-2023-Content-Articles-(batch-16-23)?node-id=456-25466&t=iqjB7zm9AtdsPASK-1 | L71: class-low | O71: https://paven.io/content/article/16ulTh3hdn7KndU6NnVaYJ
A72: 2022 Q2 | B72: SH_1.4 | C72: How do you keep a side hustle balanced? | D72: goal-retirement | G72: topic-side-hustle, topic-income | I72: profile-priorities-debtmanagement | K72: https://www.figma.com/design/i47pYiJ10vqlvx0co3h46m/Q4-2022---Q1-2023-Content-Articles-(batch-16-23)?node-id=456-25465&t=iqjB7zm9AtdsPASK-1 | L72: class-low | O72: https://paven.io/content/article/3w85EV7SQ3iBrfn4QyhizL
A73: 2022 Q2 | B73: SH_1.3 | C73: What can you do with extra income? | D73: goal-retirement | G73: topic-side-hustle, topic-income | I73: profile-priorities-debtmanagement | K73: https://www.figma.com/design/i47pYiJ10vqlvx0co3h46m/Q4-2022---Q1-2023-Content-Articles-(batch-16-23)?node-id=456-25464&t=iqjB7zm9AtdsPASK-1 | L73: class-low | O73: https://paven.io/content/article/6Qie4jKs1GkUWEqxd8Gtg2
A74: 2022 Q2 | B74: SH_1.2 | C74: What are common challenges to a side hustle? | D74: goal-retirement | G74: topic-side-hustle, topic-income | I74: profile-priorities-debtmanagement | K74: https://www.figma.com/design/i47pYiJ10vqlvx0co3h46m/Q4-2022---Q1-2023-Content-Articles-(batch-16-23)?node-id=456-25463&t=iqjB7zm9AtdsPASK-1 | L74: class-mid | O74: https://paven.io/content/article/3rR1a97Fvy09ERBVsS2Thw
A75: 2022 Q2 | B75: SH_1.1 | C75: Is a side hustle right for you? | D75: goal-retirement | G75: topic-side-hustle, topic-income | I75: profile-priorities-debtmanagement | K75: https://www.figma.com/design/i47pYiJ10vqlvx0co3h46m/Q4-2022---Q1-2023-Content-Articles-(batch-16-23)?node-id=456-25462&t=iqjB7zm9AtdsPASK-1 | L75: class-low | O75: https://paven.io/content/article/1wYhYpXAR48Y8xrnbg8sZG
A76: 2022 Q2 | B76: SMINV_1.17 | C76: What to do when it’s time to sell | G76: topic-stocks-bonds, topic-smart-investing | H76: group-investing-strategies | I76: profile-priorities-investing profile-invest-beginner profile-invest-intermediate profile-invest-advanced profile-invest-none | K76: https://www.figma.com/design/i47pYiJ10vqlvx0co3h46m/Q4-2022---Q1-2023-Content-Articles-(batch-16-23)?node-id=377-41090&t=V1quavg1MmDh9NVO-1 | L76: class-low | O76: https://paven.io/content/article/4Ng2YvpV8LrMlFjsxVpeJU
A77: 2022 Q2 | B77: SMINV_1.16 | C77: How to buy value in downturn markets | G77: topic-volatility, topic-stocks-bonds | H77: group-markets | I77: profile-priorities-investing profile-invest-beginner profile-invest-intermediate profile-invest-advanced profile-invest-none | K77: https://www.figma.com/design/i47pYiJ10vqlvx0co3h46m/Q4-2022---Q1-2023-Content-Articles-(batch-16-23)?node-id=377-41089&t=V1quavg1MmDh9NVO-1 | L77: class-low | O77: https://paven.io/content/article/1JW1sak5YCHIUTftlsnYyH
A78: 2022 Q2 | B78: SMINV_1.15 | C78: How to balance your assets | G78: topic-smart-investing, topic-stocks-bonds | H78: group-investing-strategies | I78: profile-priorities-investing profile-invest-beginner profile-invest-intermediate profile-invest-advanced profile-invest-none | K78: https://www.figma.com/design/i47pYiJ10vqlvx0co3h46m/Q4-2022---Q1-2023-Content-Articles-(batch-16-23)?node-id=377-41088&t=V1quavg1MmDh9NVO-1 | L78: class-low | O78: https://paven.io/content/article/3c09I1UZpgmQhHwpT0JSsr
A79: 2022 Q2 | B79: SMINV_1.14 | C79: How to diversify against risk | G79: topic-volatility, topic-stocks-bonds | H79: group-investing-strategies | I79: profile-priorities-investing profile-invest-beginner profile-invest-intermediate profile-invest-advanced profile-invest-none | K79: https://www.figma.com/design/i47pYiJ10vqlvx0co3h46m/Q4-2022---Q1-2023-Content-Articles-(batch-16-23)?node-id=377-41087&t=V1quavg1MmDh9NVO-1 | L79: class-low | O79: https://paven.io/content/article/43urikfZgzg2uJrCrawnP1
A80: 2022 Q2 | B80: SMINV_1.13 | C80: Five things smart investors do | G80: topic-savviness, topic-smart-investing | H80: group-investing-strategies | I80: profile-priorities-investing profile-invest-beginner profile-invest-intermediate profile-invest-advanced profile-invest-none | K80: https://www.figma.com/design/i47pYiJ10vqlvx0co3h46m/Q4-2022---Q1-2023-Content-Articles-(batch-16-23)?node-id=377-41086&t=V1quavg1MmDh9NVO-1 | L80: class-low | O80: https://paven.io/content/article/6yUQLPT9Pjn1epVxxcTk4O
A81: 2022 Q2 | B81: SMINV_1.20 | C81: Three smart buying moves | G81: topic-stocks-bonds, topic-smart-investing | H81: group-investing-strategies | I81: profile-priorities-investing profile-invest-beginner profile-invest-intermediate profile-invest-advanced profile-invest-none | K81: https://www.figma.com/design/i47pYiJ10vqlvx0co3h46m/Q4-2022---Q1-2023-Content-Articles-(batch-16-23)?node-id=374-36560&t=V1quavg1MmDh9NVO-1 | L81: class-low | O81: https://paven.io/content/article/OlaJJkToPF2JodIaSd5OX
A82: 2022 Q2 | B82: SMINV_1.19 | C82: Three ways to rebalance your risk | G82: topic-smart-investing, topic-smart-investing | H82: group-investing-strategies | I82: profile-priorities-investing profile-invest-beginner profile-invest-intermediate profile-invest-advanced profile-invest-none | K82: https://www.figma.com/design/i47pYiJ10vqlvx0co3h46m/Q4-2022---Q1-2023-Content-Articles-(batch-16-23)?node-id=374-36559&t=V1quavg1MmDh9NVO-1 | L82: class-low | O82: https://paven.io/content/article/ZeG6EWxMCaO0YRYYfmnWq
A83: 2022 Q4 | B83: EOY23_1.2 | C83: How to (still) grow your savings | D83: goal-debt-management | G83: topic-inflation, topic-debt | H83: group-how-to-save | I83: profile-priorities-budgeting profile-priorities-debtmanagement | L83: class-low | M83: Great candidate for refresh this year | O83: https://paven.io/content/article/5mfqS9Vfc864cqZOaxR0tM
A84: 2022 Q4 | B84: EOY23_1.1 | C84: Tackling debt when rates are up? | D84: goal-debt-management | G84: topic-inflation, topic-debt | H84: group-how-to-save | I84: profile-priorities-budgeting profile-priorities-debtmanagement | L84: class-low | M84: Great candidate for refresh this year | O84: https://paven.io/content/article/3PDS3KiXZd3iH4L81CGmAE
A85: 2022 Q4 | B85: RSU_1.1 | C85: Your RSUs: Basics of restricted stock units | G85: topic-rsus, topic-benefits | H85: group-benefits | I85: profile-priorities-investing profile-invest-beginner profile-invest-intermediate profile-invest-advanced profile-invest-none | K85: https://www.figma.com/design/i47pYiJ10vqlvx0co3h46m/Q4-2022---Q1-2023-Content-Articles-(batch-16-23)?node-id=456-39135&t=Q2DHer4p4jJQ3cc5-1 | L85: class-high | O85: https://paven.io/benefits/article/1P13uxOOyCx9Fik6t52DK7
A86: 2022 Q4 | B86: RSU_1.2 | C86: Your RSUs: What to know for vesting season | G86: topic-rsus, topic-benefits | H86: group-benefits | I86: profile-priorities-investing profile-invest-beginner profile-invest-intermediate profile-invest-advanced profile-invest-none | K86: https://www.figma.com/design/i47pYiJ10vqlvx0co3h46m/Q4-2022---Q1-2023-Content-Articles-(batch-16-23)?node-id=456-39136&t=Q2DHer4p4jJQ3cc5-1 | L86: class-mid | O86: https://paven.io/content/article/78VlFut1ek7HEDcnMPxCFW
A87: 2022 Q4 | B87: RSU_1.3 | C87: Your RSUs: Taxes on restricted stock units | G87: topic-taxes, topic-rsus | H87: group-benefits | I87: profile-priorities-investing profile-invest-beginner profile-invest-intermediate profile-invest-advanced profile-invest-none | K87: https://www.figma.com/design/i47pYiJ10vqlvx0co3h46m/Q4-2022---Q1-2023-Content-Articles-(batch-16-23)?node-id=456-39137&t=Q2DHer4p4jJQ3cc5-1 | L87: class-high | O87: https://paven.io/content/article/38bNEAdm4WZn9jtUZP91nV
A88: 2022 Q4 | B88: HOME_1.4 | C88: Financial finesse: Connect with a coach | G88: topic-benefits | H88: group-benefits | I88: profile-priorities-investing profile-priorities-debtmanagement profile-priorities-taxplanning | K88: https://www.figma.com/design/i47pYiJ10vqlvx0co3h46m/Q4-2022---Q1-2023-Content-Articles--batch-16-23-?node-id=459-82421&t=i5sisu6XWF9VA7BU-0 | L88: class-high | O88: https://paven.io/benefits/article/1gd9ZmQkYFEtWHRWxNeOAb
A89: 2022 Q4 | B89: Company_Match_META 2024 | C89: Meta's 401(k) match in 2024 | D89: goal-retirement | E89: lm-purposeful-learning | G89: topic-401k, topic-simulator | H89: group-benefits | I89: profile-priorities-investing profile-invest-beginner profile-invest-intermediate profile-invest-advanced profile-invest-none | L89: class-high | O89: https://paven.io/simulator/article/4m9ObHleGYAHetpJwNzLRF
A90: 2022 Q4 | B90: RET_1.11 | C90: New 401(k) and IRA maxes for 2023 | D90: goal-retirement | G90: topic-401k, topic-ira | H90: group-benefits | I90: profile-priorities-investing profile-invest-beginner profile-invest-intermediate profile-invest-advanced profile-invest-none | K90: https://www.figma.com/design/i47pYiJ10vqlvx0co3h46m/Q4-2022---Q1-2023-Content-Articles-(batch-16-23)?node-id=459-82422&t=V1quavg1MmDh9NVO-1 | L90: class-mid | O90: https://paven.io/content/article/5xjza1fH94s5LckPzkl6VD
A91: 2022 Q4 | B91: RET_1.11 | C91: New 401(k) and IRA maxes for 2023 | I91: profile-priorities-investing profile-invest-beginner profile-invest-intermediate profile-invest-advanced profile-invest-none | K91: https://www.figma.com/design/i47pYiJ10vqlvx0co3h46m/Q4-2022---Q1-2023-Content-Articles-(batch-16-23)?node-id=461-34819&t=V1quavg1MmDh9NVO-1
A92: 2022 Q4 | B92: HSA_1.1 | C92: Advantages of a health savings account (HSA) | G92: topic-hsa, topic-account-types | H92: group-account-types | I92: profile-priorities-healthcost | K92: https://www.figma.com/design/i47pYiJ10vqlvx0co3h46m/Q4-2022---Q1-2023-Content-Articles-(batch-16-23)?node-id=456-39142&t=ylcRdbapROHtfQrj-1 | L92: class-mid | O92: https://paven.io/benefits/article/5MI8Ls8IGPcUt3AJFuIzMr
A93: 2022 Q4 | B93: AC_1.17 | C93: Meta Benefits: Lyra | G93: topic-benefits | H93: group-benefits | I93: profile-priorities-healthcost | K93: https://www.figma.com/design/i47pYiJ10vqlvx0co3h46m/Q4-2022---Q1-2023-Content-Articles-(batch-16-23)?node-id=459-82425&t=V1quavg1MmDh9NVO-1 | L93: class-low | O93: https://paven.io/benefits/article/5BoGLnjCZiOA8kMCEVkPE6
A94: 2022 Q4 | B94: HSA_1.2 | C94: Investing with your health savings account | G94: topic-hsa, topic-account-types | H94: group-account-types | I94: profile-priorities-healthcost | K94: https://www.figma.com/design/i47pYiJ10vqlvx0co3h46m/Q4-2022---Q1-2023-Content-Articles-(batch-16-23)?node-id=456-39141&t=ylcRdbapROHtfQrj-1 | L94: class-low | O94: https://paven.io/content/article/6ZgnRVrA2p72oVTFaNXnxc
A95: 2022 Q4 | B95: missing tag | C95: HSA Open enrollment | I95: profile-priorities-healthcost | K95: https://www.figma.com/design/i47pYiJ10vqlvx0co3h46m/Q4-2022---Q1-2023-Content-Articles-(batch-16-23)?node-id=456-39140&t=V1quavg1MmDh9NVO-1
A96: 2022 Q4 | B96: HSA_1.3 | C96: How to choose between an HSA and an FSA | G96: topic-benefits, topic-account-types | H96: group-account-types | I96: profile-priorities-healthcost | L96: class-mid | O96: https://paven.io/content/article/xkQal080XFEz669YXK0a6
A97: 2022 Q4 | B97: EOY23_1.3 | C97: What did the market do in 2023? | G97: topic-inflation, topic-savviness | H97: group-markets | I97: profile-priorities-investing profile-invest-beginner profile-invest-intermediate profile-invest-advanced profile-invest-none | L97: class-low | O97: https://paven.io/content/article/4TXUb8E5YSXz5shgWmWpl
A98: 2022 Q4 | B98: SMINV_4.1 | C98: Investing principle: the margin of safety | G98: topic-savviness | H98: group-investing-strategies | I98: profile-priorities-investing profile-invest-beginner profile-invest-intermediate profile-invest-advanced profile-invest-none | L98: class-low | O98: https://paven.io/content/article/3PKUvGhYtuKg8oMY8Pj1cx
A99: 2022 Q4 | B99: missing tag | C99: Year End Look Back 2022: Article 1 | K99: https://www.figma.com/design/i47pYiJ10vqlvx0co3h46m/Q4-2022---Q1-2023-Content-Articles-(batch-16-23)?node-id=462-18235&t=AZaULhiHG8rTkCfU-1
A100: 2022 Q4 | B100: missing tag | C100: Year End Look Back 2022: Article 2 | K100: https://www.figma.com/design/i47pYiJ10vqlvx0co3h46m/Q4-2022---Q1-2023-Content-Articles-(batch-16-23)?node-id=462-18236&t=QfOhOC59Yq3Jb2Zy-1
...

Sheet Guidelines
A1: Article topic | B1: Group tag | C1: Topic tag | D1: Goal tag | E1: Class tag
A2: i.e. 401k | B2: group-account-types | C2: topic-401k | D2: goal-retirement
B3: group-priorities
B4: group-how-to-save
B5: group-self-care
B6: group-investing-strategies
B7: group-markets
B8: group-career
B9: group-monthly
B10: group-paven-app
B11: group-benefits

Sheet V2 New system worksheet
B1: Current ID | C1: Article title | D1: Goal (5) goal-retirement goal-emergency-fund goal-debt-management goal-kids-education goal-buying-a-home goal-buying-a-car | E1: Life Moment (5) lm-Inheritance lm-purposeful-learning lm-growing-your-family lm-combining-finances lm-relocation lm-covid | F1: Life Stage (3) -ls-early -ls-mid -ls-late | G1: Content topic (granular/specific) | H1: Secondary content topic (optional) | I1: Content group (overarching/adjacent) | J1: Profile profile-ownhome profile-wanthome profile-owncar profile-wantcar profile-spouse profile-havekids profile-wantkids profile-agingparents prorfile-havepets +more | K1: Level level-basic level-intermediate level-advanced | L1: Class (3) class-low class-mid class-high | M1: Relevant benefit for Suggestion | N1: Relevant action for Suggestion | O1: Next article in series for Suggestion | P1: Benefit | Q1: New life moment / goal ideas | R1: Notes
A2: Early Publications | B2: TT_1.4 | C2: Ways to use your pay raise | G2: topic-income | H2: topic-savviness | M2: =COUNTIF(G2:H188,N2) -> 7 | N2: {=_xlfn.UNIQUE(G2:G182)} -> topic-income | O2: {=_xlfn.UNIQUE(I2:I182)} -> 0 | P2: household-single | Q2: goal-wellbeing
A3: Early Publications | B3: LM_COM_1.4 | C3: Travel or save for emergencies | D3: goal-travel-fund goal-emergency-fund | E3: lm-combining-finances | G3: topic-resilience | I3: group-priorities | M3: =COUNTIF($G$2:$H$188,N3) -> 15 | N3: topic-resilience | O3: group-priorities | P3: household-teens | Q3: goal-paven
A4: Early Publications | B4: LM_COM_1.5 | C4: Pay off debt or buy a home? | D4: goal-debt-management goal-buying-a-home | E4: lm-combining-finances | G4: topic-resilience | I4: group-priorities | M4: =COUNTIF($G$2:$H$188,N4) -> 1 | N4: topic-relocation | O4: group-account-types
A5: Early Publications | B5: LM_RELO_1.1 | C5: Relocation 101 | E5: lm-relocation | G5: topic-relocation | I5: group-priorities | K5: level-basic | M5: =COUNTIF($G$2:$H$188,N5) -> 2 | N5: topic-car | O5: group-how-to-save
A6: Early Publications | B6: LM_RELO_1.2 | C6: Should I buy a car? | D6: goal-car | E6: lm-relocation | G6: topic-car | I6: group-priorities | M6: =COUNTIF($G$2:$H$188,N6) -> 1 | N6: topic-fsa | O6: group-self-care
A7: Early Publications | B7: LM_RELO_1.3 | C7: Save for emergencies or send money home? | D7: goal-emergency-fund goal-buying-a-home | E7: lm-growing-your-family lm-relocation | G7: topic-resilience | I7: group-priorities | M7: =COUNTIF($G$2:$H$188,N7) -> 10 | N7: topic-family | O7: group-investing-strategies
A8: Early Publications | B8: LM_RELO_1.5 | C8: Save for retirement or send money home? | D8: goal-retirement goal-buying-a-home | E8: lm-relocation | G8: topic-resilience | I8: group-priorities | M8: =COUNTIF($G$2:$H$188,N8) -> 2 | N8: topic-529 | O8: group-markets
A9: Early Publications | B9: EMF_1.1 | C9: Do I need an emergency fund? | D9: goal-emergency-fund | G9: topic-resilience | I9: group-priorities | M9: =COUNTIF($G$2:$H$188,N9) -> 2 | N9: topic-roth-ira | O9: group-career
A10: Early Publications | B10: EMF_1.2 | C10: Saving for the unknown | D10: goal-emergency-fund | G10: topic-resilience | I10: group-priorities | M10: =COUNTIF($G$2:$H$188,N10) -> 1 | N10: topic-brokerage | O10: group-monthly
A11: Early Publications | B11: EMF_1.3 | C11: Where to stash emergency funds | D11: goal-emergency-fund | G11: topic-resilience | I11: group-account-types | M11: =COUNTIF($G$2:$H$188,N11) -> 3 | N11: topic-bad-debt | O11: group-paven-app
A12: Early Publications | B12: FSA_2.1 | C12: How to make the most of your FSA | G12: topic-fsa | I12: group-account-types | M12: =COUNTIF($G$2:$H$188,N12) -> 2 | N12: topic-student-loans
A13: Early Publications | B13: EMF_1.5 | C13: Setting up automatic transfers | D13: goal-emergency-fund | G13: topic-resilience | I13: group-how-to-save | M13: =COUNTIF($G$2:$H$188,N13) -> 2 | N13: topic-credit-cards
A14: Early Publications | B14: EMF_1.6 | C14: How to boost emergency funds | D14: goal-emergency-fund | G14: topic-resilience | I14: group-how-to-save | M14: =COUNTIF($G$2:$H$188,N14) -> 1 | N14: topic-credit-score
A15: Early Publications | B15: SFC_1.1 | C15: 3 reasons to start saving now | D15: goal-kids-ed | G15: topic-family | I15: group-priorities | M15: =COUNTIF($G$2:$H$188,N15) -> 0 | N15: 0
A16: Early Publications | B16: SFC_1.2 | C16: Kids’ education vs other goals | D16: goal-kids-ed | G16: topic-family | I16: group-priorities | M16: =COUNTIF($G$2:$H$188,N16) -> 4 | N16: topic-retirement-planning
A17: Early Publications | B17: SFC_1.3 | C17: Education account types | D17: goal-kids-ed | G17: topic-family | I17: group-account-types | M17: =COUNTIF($G$2:$H$188,N17) -> 9 | N17: topic-401k
A18: Early Publications | B18: SFC_1.4 | C18: The 529 plan, explained | D18: goal-kids-ed | G18: topic-529 | I18: group-account-types | M18: =COUNTIF($G$2:$H$188,N18) -> 28 | N18: topic-benefits
A19: Early Publications | B19: SFC_1.5 | C19: Using a Roth IRA to save | D19: goal-kids-ed | G19: topic-roth-ira | I19: group-account-types | M19: =COUNTIF($G$2:$H$188,N19) -> 9 | N19: topic-travel
A20: Early Publications | B20: SFC_1.6 | C20: Using a brokerage account to save | D20: goal-kids-ed | G20: topic-brokerage | I20: group-account-types | M20: =COUNTIF($G$2:$H$188,N20) -> 15 | N20: topic-savviness
A21: Early Publications | B21: SFC_1.7 | C21: Other ways to save for education | D21: goal-kids-ed | G21: topic-family | I21: group-how-to-save | M21: =COUNTIF($G$2:$H$188,N21) -> 18 | N21: topic-stocks-bonds
A22: Early Publications | B22: MM_1.7 | C22: College coaching from Bright Horizons | D22: goal-kids-ed | G22: topic-family | H22: topic-benefits | M22: =COUNTIF($G$2:$H$188,N22) -> 4 | N22: topic-industries
A23: Early Publications | B23: DEB_1.1 | C23: Good debt vs bad debt | D23: goal-debt-management-management | G23: topic-bad-debt | I23: group-priorities | M23: =COUNTIF($G$2:$H$188,N23) -> 7 | N23: topic-volatility
A24: Early Publications | B24: DEB_1.2 | C24: Dealing with student loan debt | D24: goal-debt-management | G24: topic-student-loans | I24: group-how-to-save | M24: =COUNTIF($G$2:$H$188,N24) -> 5 | N24: topic-skills
A25: Early Publications | B25: DEB_1.3 | C25: How credit card debt works | D25: goal-debt-management | G25: topic-credit-cards | H25: topic-resilience | K25: level-basic | M25: =COUNTIF($G$2:$H$188,N25) -> 5 | N25: topic-side-hustle
A26: Early Publications | B26: DEB_1.4 | C26: Tips to cut credit card debt | D26: goal-debt-management | G26: topic-credit-cards | H26: topic-savviness | M26: =COUNTIF($G$2:$H$188,N26) -> 3 | N26: topic-hsa
A27: Early Publications | B27: DEB_1.5 | C27: Refinance your student loans | D27: goal-debt-management | G27: topic-student-loans | H27: topic-benefits | M27: =COUNTIF($G$2:$H$188,N27) -> 2 | N27: topic-financial-finesse
A28: Early Publications | B28: DEB_1.7 | C28: Credit scores 101 | D28: goal-debt-management | G28: topic-credit-score | H28: topic-resilience | K28: level-basic | M28: =COUNTIF($G$2:$H$188,N28) -> 4 | N28: topic-rsus
A29: Early Publications | B29: DEB_1.8 | C29: Track your debt payments | D29: goal-debt-management | G29: topic-bad-debt | I29: group-how-to-save | M29: =COUNTIF($G$2:$H$188,N29) -> 6 | N29: topic-taxes
A30: Early Publications | B30: RET_1.1 | C30: Retiring on your own terms | D30: goal-retirement | I30: group-priorities | M30: =COUNTIF($G$2:$H$188,N30) -> 3 | N30: topic-crypto
A31: Early Publications | B31: RET_1.2 | C31: Common barriers to saving | D31: goal-retirement | I31: group-how-to-save | M31: =COUNTIF($G$2:$H$188,N31) -> 5 | N31: topic-insurance
A32: Early Publications | B32: RET_1.3 | C32: Define your target number | D32: goal-retirement | I32: group-priorities | M32: =COUNTIF($G$2:$H$188,N32) -> 3 | N32: topic-estate-planning
A33: Early Publications | B33: RET_1.4 | C33: Add your post-retirement work | D33: goal-retirement | G33: topic-retirement-planning | I33: group-how-to-save | M33: =COUNTIF($G$2:$H$188,N33) -> 4 | N33: topic-first-home
A34: Early Publications | B34: RET_1.5 | C34: 401(k) basics | D34: goal-retirement | G34: topic-401k | I34: group-account-types | M34: =COUNTIF($G$2:$H$188,N34) -> 7 | N34: topic-inflation
A35: Early Publications | B35: RET_1.6 | C35: Your Fidelity 401(k) options | D35: goal-retirement | G35: topic-401k | H35: topic-benefits | M35: =COUNTIF($G$2:$H$188,N35) -> 5 | N35: topic-budget
A36: Early Publications | B36: RET_1.8 | C36: Is a 401(k) loan a good option? | D36: goal-retirement | G36: topic-401k | I36: group-account-types | M36: =COUNTIF($G$2:$H$188,N36) -> 7 | N36: topic-health
A37: Early Publications | B37: RET_1.10 | C37: The basics of Meta's 401(k) plan | D37: goal-retirement | G37: topic-401k | I37: group-account-types | M37: =COUNTIF($G$2:$H$188,N37) -> 4 | N37: topic-caregiving
A38: Early Publications | B38: GYF_1.1 | C38: Align your family's financial needs | E38: lm-growing-your-family lm-combining-finances | G38: topic-family | I38: group-priorities | M38: =COUNTIF($G$2:$H$188,N38) -> 7 | N38: topic-onboarding
A39: Early Publications | B39: GYF_1.9 | C39: Buying a home for your family | D39: goal-buying-a-home | E39: lm-growing-your-family lm-combining-finances | G39: topic-family | I39: group-priorities | M39: =COUNTIF($G$2:$H$188,N39) -> 3 | N39: topic-partner
A40: Early Publications | B40: GYF_1.10 | C40: Setting your kid up for future success | D40: goal-kids-ed | E40: lm-growing-your-family lm-combining-finances | G40: topic-family | I40: group-priorities | M40: =COUNTIF($G$2:$H$188,N40) -> 3 | N40: topic-inheritance
A41: Early Publications | B41: INH_1.4 | C41: Seeking help with grief | E41: lm-inheritance | G41: topic-benefits | I41: group-self-care | M41: =COUNTIF($G$2:$H$188,N41) -> 2 | N41: topic-lenders
A42: Early Publications | B42: TF_1.1 | C42: Travel today and save for tomorrow | D42: goal-travel | G42: topic-travel | I42: group-priorities | M42: =COUNTIF($G$2:$H$188,N42) -> 2 | N42: topic-charity
A43: Early Publications | B43: TF_1.2 | C43: What kind of traveler are you? | D43: goal-travel | G43: topic-travel | I43: group-priorities | M43: =COUNTIF($G$2:$H$188,N43) -> 3 | N43: topic-new-baby
A44: Early Publications | B44: TF_1.3 | C44: Travel fund strategies | D44: goal-travel | G44: topic-travel | I44: group-how-to-save | M44: =COUNTIF($G$2:$H$188,N44) -> 4 | N44: topic-simulator
A45: Early Publications | B45: TF_1.4 | C45: Find like-minded travel companions | D45: goal-travel | G45: topic-travel | I45: group-self-care | M45: =COUNTIF($G$2:$H$188,N45) -> 1 | N45: topic-mortgages
A46: Early Publications | B46: TF_1.5 | C46: Ways to save on trips | D46: goal-travel | G46: topic-travel | I46: group-how-to-save | M46: =COUNTIF($G$2:$H$188,N46) -> 0
A47: Early Publications | B47: TF_1.6 | C47: Sticking to a trip budget | D47: goal-travel | G47: topic-travel | I47: group-how-to-save | M47: =COUNTIF($G$2:$H$188,N47) -> 0
A48: Early Publications | B48: TF_1.7 | C48: Saving for regular trips | D48: goal-travel | G48: topic-travel | I48: group-how-to-save | M48: =COUNTIF($G$2:$H$188,N48) -> 0
A49: Early Publications | B49: TF_1.8 | C49: Personal travel & Meta benefits | D49: goal-travel | G49: topic-travel | H49: topic-benefits | M49: =COUNTIF($G$2:$H$188,N49) -> 0
A50: Early Publications | B50: SMINV_1.1 | C50: What is smart investing? | G50: topic-savviness | I50: group-investing-strategies | K50: level-basic | M50: =COUNTIF($G$2:$H$188,N50) -> 0
A51: Early Publications | B51: SMINV_1.2 | C51: Why smart investing? | G51: topic-savviness | I51: group-investing-strategies | K51: level-basic | M51: =COUNTIF($G$2:$H$188,N51) -> 0
A52: Early Publications | B52: SMINV_1.3 | C52: Choosing to be a smart investor | G52: topic-savviness | I52: group-investing-strategies | K52: level-basic | M52: =COUNTIF($G$2:$H$188,N52) -> 0
A53: Early Publications | B53: SMINV_1.4 | C53: Stocks and bonds: the basics | G53: topic-stocks-bonds | I53: group-investing-strategies | K53: level-basic | M53: =COUNTIF($G$2:$H$188,N53) -> 0
A54: Early Publications | B54: SMINV_1.5 | C54: Smart investing strategies | G54: topic-savviness | I54: group-investing-strategies | K54: level-basic | M54: =COUNTIF($G$2:$H$188,N54) -> 0
A55: Early Publications | B55: SMINV_1.6 | C55: Map your smart investor route | G55: topic-savviness | I55: group-investing-strategies | M55: =COUNTIF($G$2:$H$188,N55) -> 0
A56: Early Publications | B56: SMINV_1.7 | C56: Emerging and evolving industries | G56: topic-industries | I56: group-investing-strategies | M56: =COUNTIF($G$2:$H$188,N56) -> 0
A57: Early Publications | B57: SMINV_1.8 | C57: Why should you invest? | G57: topic-savviness | I57: group-investing-strategies | K57: level-basic | M57: =COUNTIF($G$2:$H$188,N57) -> 0
A58: Early Publications | B58: SMINV_1.9 | C58: Is now a good time to invest? | G58: topic-savviness | I58: group-markets | K58: level-basic | M58: =COUNTIF($G$2:$H$188,N58) -> 0
A59: Early Publications | B59: SMINV_1.10 | C59: Can you time the market? | G59: topic-savviness | I59: group-markets | M59: =COUNTIF($G$2:$H$188,N59) -> 0
A60: Early Publications | B60: SMINV_1.11 | C60: Market volatility: How to navigate | G60: topic-volatility | I60: group-markets | M60: =COUNTIF($G$2:$H$188,N60) -> 0
A61: Early Publications | B61: SMINV_1.12 | C61: How to make money in a downturn market | G61: topic-volatility | I61: group-markets | M61: =COUNTIF($G$2:$H$188,N61) -> 0
A62: Early Publications | B62: SMINV_1.13 | C62: Five things smart investors do | G62: topic-savviness | I62: group-investing-strategies | M62: =COUNTIF($G$2:$H$188,N62) -> 0
A63: Early Publications | B63: SMINV_1.14 | C63: How to diversify against risk | G63: topic-volatility | I63: group-investing-strategies | M63: =COUNTIF($G$2:$H$188,N63) -> 0
A64: Early Publications | B64: SMINV_1.15 | C64: How to balance your assets | G64: topic-stocks-bonds | I64: group-investing-strategies | M64: =COUNTIF($G$2:$H$188,N64) -> 0
A65: Early Publications | B65: SMINV_1.16 | C65: How to buy value in downturn markets | G65: topic-volatility | I65: group-markets | M65: =COUNTIF($G$2:$H$188,N65) -> 0
A66: Early Publications | B66: SMINV_1.17 | C66: What to do when it’s time to sell | G66: topic-stocks-bonds | I66: group-investing-strategies | M66: =COUNTIF($G$2:$H$188,N66) -> 0
A67: Early Publications | B67: SMINV_1.18 | C67: Rising interest rates: Can you stay in the market? | G67: topic-savviness | I67: group-markets | M67: =COUNTIF($G$2:$H$188,N67) -> 0
A68: Early Publications | B68: SMINV_1.19 | C68: Rising interest rates: Three ways to rebalance your risk | G68: topic-stocks-bonds | I68: group-investing-strategies | M68: =COUNTIF($G$2:$H$188,N68) -> 0
A69: Early Publications | B69: SMINV_1.20 | C69: Three smart buying moves | G69: topic-stocks-bonds | I69: group-investing-strategies | M69: =COUNTIF($G$2:$H$188,N69) -> 0
A70: Early Publications | B70: ES_1.1 | C70: Enhance your skills to enhance your career | E70: lm-purposeful-learning | G70: topic-stocks-bonds | I70: group-career | M70: =COUNTIF($G$2:$H$188,N70) -> 0
A71: Early Publications | B71: ES_1.2 | C71: How do I fulfill my financial and career goals? | E71: lm-purposeful-learning | G71: topic-skills | I71: group-career | M71: =COUNTIF($G$2:$H$188,N71) -> 0
A72: Early Publications | B72: ES_1.3 | C72: Common learning paths to enhance skills | E72: lm-purposeful-learning | G72: topic-skills | I72: group-career | M72: =COUNTIF($G$2:$H$188,N72) -> 0
A73: Early Publications | B73: ES_1.4 | C73: How can Meta support your growth? | E73: lm-purposeful-learning | G73: topic-benefits | I73: group-career | M73: =COUNTIF($G$2:$H$188,N73) -> 0
A74: Early Publications | B74: SH_1.1 | C74: Is a side hustle right for you? | D74: goal-retirement | G74: topic-side-hustle | H74: topic-income | K74: level-basic | M74: =COUNTIF($G$2:$H$188,N74) -> 0
A75: Early Publications | B75: SH_1.2 | C75: What are common challenges to a side hustle? | D75: goal-retirement | G75: topic-side-hustle | H75: topic-income | M75: =COUNTIF($G$2:$H$188,N75) -> 0
A76: Early Publications | B76: SH_1.3 | C76: What to do with extra income from a side hustle? | D76: goal-retirement | G76: topic-side-hustle | H76: topic-income | M76: =COUNTIF($G$2:$H$188,N76) -> 0
A77: Early Publications | B77: SH_1.4 | C77: How do you keep a side hustle balanced? | D77: goal-retirement | G77: topic-side-hustle | H77: topic-income | M77: =COUNTIF($G$2:$H$188,N77) -> 0
A78: Early Publications | B78: SH_1.5 | C78: What are the rewards of a side hustle? | D78: goal-retirement | G78: topic-side-hustle | H78: topic-income | M78: =COUNTIF($G$2:$H$188,N78) -> 0
A79: Q4 2022 Publications | B79: HSA_1.1 | C79: Advantages of a health savings account (HSA) | G79: topic-hsa | I79: group-account-types | K79: level-basic | M79: =COUNTIF($G$2:$H$188,N79) -> 0
A80: Q4 2022 Publications | B80: HSA_1.2 | C80: Investing with your health savings account | G80: topic-hsa | I80: group-investing-strategies | M80: =COUNTIF($G$2:$H$188,N80) -> 0
A81: Q4 2022 Publications | B81: HSA_1.3 | C81: How to choose between an HSA and an FSA | G81: topic-benefits | I81: group-priorities | M81: =COUNTIF($G$2:$H$188,N81) -> 0
A82: Q4 2022 Publications | B82: RET_1.11 | C82: New 401(k) and IRA maxes for 2024 | D82: goal-retirement | G82: topic-401k | H82: topic-ira | M82: =COUNTIF($G$2:$H$188,N82) -> 0
A83: Q4 2022 Publications | B83: HOME_1.4 | C83: Connect with a coach | G83: topic-financial-finesse | H83: topic-benefits | M83: =COUNTIF($G$2:$H$188,N83) -> 0
A84: Q4 2022 Publications | B84: DEB_1.6 | C84: Feeling overwhelmed? Get support from Lyra | D84: goal-debt-management | G84: topic-benefits | I84: group-self-care | M84: =COUNTIF($G$2:$H$188,N84) -> 0
A85: Q4 2022 Publications | B85: RSU_1.1 | C85: Your RSUs: Basics of restricted stock units | G85: topic-rsus | H85: topic-benefits | K85: level-basic | M85: =COUNTIF($G$2:$H$188,N85) -> 0
A86: Q4 2022 Publications | B86: RSU_1.2 | C86: Your RSUs: What to know for vesting season | G86: topic-rsus | H86: topic-benefits | M86: =COUNTIF($G$2:$H$188,N86) -> 0
A87: Q4 2022 Publications | B87: RSU_1.3 | C87: Your RSUs: Taxes on restricted stock units | G87: topic-taxes | H87: topic-rsus | M87: =COUNTIF($G$2:$H$188,N87) -> 0
A88: Q4 2022 Publications | B88: SMINV_4.1 | C88: Finding the margin of safety | G88: topic-savviness | I88: group-investing-strategies | M88: =COUNTIF($G$2:$H$188,N88) -> 0
A89: Q1 2023 Publications | B89: CRY_1.1 | C89: Crypto in 2023: where are we now? | G89: topic-crypto | I89: group-markets | K89: level-basic | M89: =COUNTIF($G$2:$H$188,N89) -> 0
A90: Q1 2023 Publications | B90: LI_2.1 | C90: Life Insurance: cover your loved ones | E90: lm-growing-your-family lm-combining-finances | G90: topic-insurance | H90: topic-benefit | M90: =COUNTIF($G$2:$H$188,N90) -> 0
A91: Q1 2023 Publications | B91: SMINV_2.1 | C91: Bond market part 1: are bonds safe? | G91: topic-stocks-bonds | I91: group-investing-strategies | M91: =COUNTIF($G$2:$H$188,N91) -> 0
A92: Q1 2023 Publications | B92: LI_2.2 | C92: Choosing a life insurance plan | E92: lm-growing-your-family lm-combining-finances | G92: topic-insurance | H92: topic-resilience | M92: =COUNTIF($G$2:$H$188,N92) -> 0
A93: Q1 2023 Publications | B93: TAX_1.2 | C93: Tax credits on clean energy in 2024 | D93: goal-car goal-buying-a-home | G93: topic-taxes | I93: group-how-to-save | M93: =COUNTIF($G$2:$H$188,N93) -> 0
A94: Q1 2023 Publications | B94: CRY_1.2 | C94: Crypto exchanges: spotting the risks | G94: topic-crypto | I94: group-markets | M94: =COUNTIF($G$2:$H$188,N94) -> 0
A95: Q1 2023 Publications | B95: RSU_1.4 | C95: Your RSUs: what’s their actual value today? | G95: topic-rsus | H95: topic-savviness | M95: =COUNTIF($G$2:$H$188,N95) -> 0
A96: Q1 2023 Publications | B96: SMINV_2.2 | C96: Bond market part 2: A guide for inflation | G96: topic-stocks-bonds | H96: topic-inflation | M96: =COUNTIF($G$2:$H$188,N96) -> 0
A97: Q1 2023 Publications | B97: BEN24_1.5 | C97: Ways to use your bonus pay | G97: topic-income | H97: topic-benefits | M97: =COUNTIF($G$2:$H$188,N97) -> 0
A98: Q1 2023 Publications | B98: TAX_1.4 | C98: Skip 529 taxes with Roth IRA transfers | D98: goal-kids-ed | G98: topic-roth-ira | H98: topic-529 | M98: =COUNTIF($G$2:$H$188,N98) -> 0
A99: Q1 2023 Publications | B99: LI_2.3 | C99: Life Insurance: is it time? | E99: lm-growing-your-family lm-combining-finances | G99: topic-insurance | I99: group-priorities | M99: =COUNTIF($G$2:$H$188,N99) -> 0
A100: Q1 2023 Publications | B100: SMINV_2.3 | C100: Bond market part 3: Bonds and SV Bank fallout | G100: topic-stocks-bonds | H100: topic-volatility | M100: =COUNTIF($G$2:$H$188,N100) -> 0
...

Sheet V1 New system worksheet
B1: Article title | C1: Goal (5) goal-retirement goal-emergency-fund goal-debt-management goal-kids-education goal-buying-a-home | D1: Life Moment (5) lm-Inheritance lm-purposeful-learning lm-growing-your-family lm-combining-finances lm-relocation lm-covid | E1: Life Stage (3) -ls-early -ls-mid -ls-late | F1: Content subject (granular/specific) | G1: Content family (overarching/adjacent) | I1: Class (3) class-low class-mid class-high | J1: New life moment / goal ideas | K1: Relevant benefit for Suggestion | L1: Relevant action for Suggestion | M1: Next article in series for Suggestion | N1: Level level-basic level-intermediate level-advanced | O1: Notes
B2: 401k limi updates 2024 | C2: goal-retirement | D2: NA | E2: NA | F2: topic-401k | G2: topic-retirement-accounts | J2: goal-car | K2: Schwab | L2: 401k vehicle setup | O2: We may want to be more granular on most popular topics, but more general on a low engagement topics
B3: IRA basics | C3: goal-retirement | D3: NA | E3: NA | F3: topic-IRA | G3: topic-retirement-accounts
B4: 529 basics | C4: goal-kids-education | D4: lm-growing your family | F4: topic-529 | G4: topic-kids
B5: Bonds | F5: Investing
F6: topics-bonds | G6: topic-investing
B7: Buying a car | C7: goal-car | G7: Crypto
B8: Side hustle | G8: RSU
F9: Family
C10: Kids ed | F10: Family
C11: Retirement
G12: Account types
D13: Retirement | G13: Account types
D14: Kids ed | G14: Account types
A17: Early Publications
A18: TT_1.4 | B18: Ways to use your pay raise | C18: goal-wellbeing | D18: lm-budgeting | E18: ls-all | F18: topic-pay-raise | G18: topic-income
A19: LM_COM_1.4 | B19: Travel or save for emergencies | C19: goal-travel-fund goal-emergency-fund | D19: lm-combining-finances | E19: ls-mid | F19: topic-spending | G19: topic-tradeoffs
A20: LM_COM_1.5 | B20: Pay off debt or buy a home? | C20: goal-debt goal-buying-a-home | D20: lm-combining-finances | E20: ls-mid | F20: topic-spending | G20: topic-tradeoffs
A21: LM_RELO_1.1 | B21: Relocation 101 | C21: goal-wellbeing | D21: lm-relocation | E21: ls-early | F21: topic-relocation | G21: topic-basics
A22: LM_RELO_1.2 | B22: Should I buy a car?
A23: LM_RELO_1.3 | B23: Save for emergencies or send money home?
A24: LM_RELO_1.5 | B24: Save for retirement or send money home?
A25: EMF_1.1 | B25: Do I need an emergency fund?
A26: EMF_1.2 | B26: Saving for the unknown
A27: EMF_1.3 | B27: Where to stash emergency funds
A28: FSA_2.1 | B28: How to make the most of your FSA
A29: EMF_1.5 | B29: Setting up automatic transfers
A30: EMF_1.6 | B30: How to boost emergency funds
A31: SFC_1.1 | B31: 3 reasons to start saving now
A32: SFC_1.2 | B32: Kids’ education vs other goals
A33: SFC_1.3 | B33: Education account types
... A38: MM_1.7 | B38: College coaching from Bright Horizons
A39: DEB_1.1 | B39: Good debt vs bad debt | C39: goal-debt | D39: lm-budgeting | E39: ls-early | F39: topic-debt | G39: topic-strategies
A40: DEB_1.2 | B40: Dealing with student loan debt | C40: goal-debt | D40: lm-student-loans | E40: ls-early | F40: topic-student-loans | G40: topic-strategies
A41: DEB_1.3 | B41: How credit card debt works | C41: goal-debt | D41: lm-budgeting | E41: ls-early | F41: topic-credit-cards | G41: topic-basics
A42: DEB_1.4 | B42: Tips to cut credit card debt | C42: goal-debt | D42: lm-budgeting | E42: ls-early | F42: topic-debt | G42: topic-strategies
A43: DEB_1.5 | B43: Refinance your student loans | C43: goal-debt | D43: lm-student-loans | E43: ls-early | F43: topic-debt | G43: topic-strategies
A44: DEB_1.6 | B44: Feeling overwhelmed? Get support
A45: DEB_1.7 | B45: Credit scores 101
A46: DEB_1.8 | B46: Track your debt payments
A47: RET_1.1 | B47: Retiring on your own terms
A48: RET_1.2 | B48: Common barriers to saving
A49: RET_1.3 | B49: Define your target number
A50: RET_1.4 | B50: Add your post-retirement work
A51: RET_1.5 | B51: 401(k) basics
A52: RET_1.6 | B52: Your Fidelity 401(k) options
A53: RET_1.8 | B53: Is a 401(k) loan a good option?
A54: RET_1.10 | B54: The basics of Meta's 401(k) plan
A55: GYF_1.1 | B55: Align your family's financial needs
... A66: TF_1.8 | B66: Personal travel & Meta benefits
A67: SMINV_1.1 | B67: What is smart investing? | D67: lm-investing | E67: ls-all | F67: topic-investing | G67: topic-basics
A68: SMINV_1.2 | B68: Why smart investing? | D68: lm-investing | E68: ls-all | F68: topic-investing | G68: topic-basics
A69: SMINV_1.3 | B69: Choosing to be a smart investor | D69: lm-investing | E69: ls-all | F69: topic-investing | G69: topic-basics
A70: SMINV_1.4 | B70: Stocks and bonds: the basics | D70: lm-investing | E70: ls-all | F70: topic-stocks-and-bonds | G70: topic-basics
A71: SMINV_1.5 | B71: Smart investing strategies | D71: lm-investing | E71: ls-all | F71: topic-investing | G71: topic-basics
A72: SMINV_1.6 | B72: Map your smart investor route
A73: SMINV_1.7 | B73: Emerging and evolving industries
A74: SMINV_1.8 | B74: Why should you invest?
A75: SMINV_1.9 | B75: Is now a good time to invest?
A76: SMINV_1.10 | B76: Can you time the market?
A77: SMINV_1.11 | B77: Market volatility: How to navigate | D77: lm-investing | E77: ls-all | F77: topic-investing | G77: topic-markets
A78: SMINV_1.12 | B78: How to make money in a downturn market | D78: lm-investing | E78: ls-all | F78: topic-investing | G78: topic-markets
A79: SMINV_1.13 | B79: Five things smart investors do | D79: lm-investing | E79: ls-all | F79: topic-investing | G79: topic-strategies
A80: SMINV_1.14 | B80: How to diversify against risk | D80: lm-investing | E80: ls-all | F80: topic-investing | G80: topic-strategies
A81: SMINV_1.15 | B81: How to balance your assets | D81: lm-investing | E81: ls-all | F81: topic-investing | G81: topic-strategies
A82: SMINV_1.16 | B82: How to buy value in downturn markets
A83: SMINV_1.17 | B83: What to do when it’s time to sell
A84: SMINV_1.18 | B84: Rising interest rates: Can you stay in the market?
A85: SMINV_1.19 | B85: Rising interest rates: Three ways to rebalance your risk
A86: SMINV_1.20 | B86: Three smart buying moves
A87: ES_1.1 | B87: Enhance your skills to enhance your career
A88: ES_1.2 | B88: How do I fulfill my financial and career goals?
A89: ES_1.3 | B89: Common learning paths to enhance skills
A90: ES_1.4 | B90: How can Meta support your growth?
A91: SH_1.1 | B91: Is a side hustle right for you? | C91: goal-retirement | D91: lm-side-hustle | E91: ls-all | F91: topic-side-hustle | G91: topic-basics
A92: SH_1.2 | B92: What are common challenges to a side hustle? | C92: goal-retirement | D92: lm-side-hustle | E92: ls-all | F92: topic-side-hustle | G92: topic-strategies
A93: SH_1.3 | B93: What to do with extra income from a side hustle? | C93: goal-retirement | D93: lm-side-hustle | E93: ls-all | F93: topic-side-hustle | G93: topic-income
A94: SH_1.4 | B94: How do you keep a side hustle balanced? | C94: goal-retirement | D94: lm-side-hustle | E94: ls-all | F94: topic-side-hustle | G94: topic-tradeoffs
A95: SH_1.5 | B95: What are the rewards of a side hustle? | C95: goal-retirement | D95: lm-side-hustle | E95: ls-all | F95: topic-side-hustle | G95: topic-strategies
A96: Q4 2022 Publications
A97: HSA_1.1 | B97: Advantages of a health savings account (HSA) | C97: goal-wellbeing | D97: lm-saving | E97: ls-all | F97: topic-hsa | G97: topic-basics
A98: HSA_1.2 | B98: Investing with your health savings account | C98: goal-wellbeing | D98: lm-saving | E98: ls-all | F98: topic-hsa | G98: topic-strategies
A99: HSA_1.3 | B99: How to choose between an HSA and an FSA | C99: goal-wellbeing | D99: lm-saving | E99: ls-all | F99: topic-hsa topic-fsa | G99: topic-tradeoffs
A100: RET_1.11 | B100: New 401(k) and IRA maxes for 2024 | C100: goal-retirement | D100: lm-saving | E100: ls-all | F100: topic-401(k) topic-ira | G100: topic-benefit-updates
A101: HOME 1.4 | B101: Connect with a coach | C101: goal-wellbeing | D101: lm-coaching | E101: ls-all | F101: topic-financial-finesse | G101: topic-coaching
A102: TAX_1.1 | B102: Connect with a tax advisor | C102: goal-wellbeing | D102: lm-coaching | E102: ls-all | F102: topic-taxes | G102: topic-coaching
A103: DEB_1.6 | B103: Feeling overwhelmed? Get support from Lyra
A104: RSU_1.1 | B104: Your RSUs: Basics of restricted stock units
A105: RSU_1.2 | B105: Your RSUs: What to know for vesting season
A106: RSU_1.3 | B106: Your RSUs: Taxes on restricted stock units
A107: EOY_1.1 | B107: Part 1: Investing trends for December
A108: EOY_1.2 | B108: Part 2: Saving in the shadow of rising inflation
A109: EOY_1.3 | B109: Part 3: Tackling debt during inflation
A110: EOY_1.4 | B110: Part 4: Invest (now) for 2023?
A111: EOY_1.5 | B111: Part 5: Finding the margin of safety
A112: Q1 2023 Publications
A113: TT23_1.1 | B113: January: What’s ahead? | D113: lm-staying-informed | E113: ls-all | F113: topic-investing | G113: topic-timely
A114: BEN23_1.1 | B114: Wellness reimbursement in 2024 | C114: goal-wellbeing | D114: lm-staying-healthy | E114: ls-all | F114: topic-life@-choice | G114: topic-strategies
A115: CRY_1.1 | B115: Crypto in 2023: where are we now? | D115: lm-investing | E115: ls-all | F115: topic-crypto | G115: topic-basics
A116: BEN23_1.2 | B116: Benefit changes for 2024 | D116: lm-staying-informed | E116: ls-all | F116: topic- | G116: topic-benefit-updates
...

Sheet Sheet9
A1: TF_1.4 TF_1.8 SMINV_1.1 SMINV_1.4 SMINV_1.7 SMINV_1.8 SMINV_1.12 SMINV_1.13 SMINV_1.17 SMINV_1.18 SMINV_1.20 ES_1.4 SH_1.2 SH_1.4 HOME 1.4 CRY_1.1 LI_2.1 SMINV_2.1 BEN24_1.5 HSA_1.4 BAH_2.1 SMINV_2.6 SMINV_2.7 BEN23_1.10 SMINV_2.8 INH_2.1 GOAL_1.3 BEN23_2.6 GYF_2.3 Tax Refund_SIMULATOR BEN24_1.1 BEN24_1.2 FFTAX_1.1 TT24_1.3

Sheet Export of publications with tag
A1: title | B1: id | C1: identifier | D1: contentType | E1: date | F1: tags__001 | G1: tags__002 | H1: tags__003 | I1: tags__004 | J1: tags__005 | K1: tags__006 | L1: tags__007 | M1: tags__008 | N1: tags__009 | O1: tags__010 | P1: tags__011 | Q1: tags__012 | R1: tags__013 | S1: tags__014 | T1: tags__015 | U1: tags__016
A2: Caring for your parents with Wellthy | B2: 5ubss1n8Gur0R55hMiXIfS | C2: BEN23_2.4 | D2: exploreArticleCard | E2: 2023-08-22T21:46:44.689Z | F2: topic-caregiving | G2: benefit-wellthy
A3: How to set your first goal in Paven | B3: owseBAvFJG0YhuvrzfRpI | C3: GOAL_1.2 | D3: exploreArticleCard | E3: 2023-08-22T21:45:07.414Z | F3: topic-competing-goals | G3: topic-welcome
A4: New ways to save today | B4: 2uVkUsniZpnSL93XUw7D3N | C4: SMINV_3.3 | D4: exploreArticleCard | E4: 2023-08-22T18:10:09.450Z | F4: topic-smart-investing | G4: goal-smart-investing
A5: August: is it shrinkflation summer? | B5: 1IqFt8WpM4uacZfsTcGUiz | C5: TT23_1.8 | D5: exploreArticleCard | E5: 2023-08-11T22:26:55.696Z | F5: topic-inflation | G5: collection-timely-topics
A6: Caregiver benefits: get support with Meta | B6: 3KYnw2do1wxFB6Q1yqiXlb | C6: BEN23_2.3 | D6: exploreBenefitCard | E6: 2023-08-11T22:23:30.746Z | F6: topic-caregiving
A7: Inheritance: planning with care | B7: 1duNyvJJQXqpJzwPwiAgHa | C7: INH_2.1 | D7: exploreBenefitCard | E7: 2023-08-11T22:17:30.303Z | F7: topic-inheritance
A8: Meta’s estate planning benefit | B8: 2GsW4fbTdPK4dUzW0i2d7o | C8: EST_1.1 | D8: exploreBenefitCard | E8: 2023-08-11T21:21:25.137Z | F8: collection-meta-benefits
A9: Estate planning | B9: 694r5jryKhoDyV0sQnFLQy | C9: EST_vid_1 | D9: exploreVideoCard | E9: 2023-08-11T20:13:04.871Z | F9: benefit-estate-planning
A10: Planning for retirement beyond your 401(k) | B10: 6RCplWXPy3wJ3UMlPOBXr4 | C10: Occam's Razor 2023 | D10: simulatorContent | E10: 2023-08-09T12:13:47.759Z | F10: topic-retirement | G10: topic-401(k) | H10: topic-pre-tax-401(k) | I10: topic-roth-401(k) | J10: topic-after-tax-401(k) | K10: topic-ira | L10: topic-roth-ira | M10: topic-account-types | N10: topic-401 | O10: topic-401k | P10: collection-401(k)-retirement | Q10: collection-401(k)-withdrawals-retirement | R10: collection-retirement
A11: Meta life insurance: cover your loved ones | B11: KqhuSFoODJlrEVoBt3Eqa | C11: LI_2.1 | D11: exploreBenefitCard | E11: 2023-08-08T18:47:32.692Z | F11: Life Insurance- topic | G11: Life Insurance - collection | H11: collection-meta-benefits
A12: Investing in the future of health | B12: 5i9cosAfHxAXEfBxaIez5m | C12: SMINV_3.2 | D12: exploreArticleCard | E12: 2023-08-04T19:37:31.037Z | F12: topic-smart-investing | G12: topic-health | H12: topic-stock
A13: Investors: ready for a fresh start? | B13: 1PwhRz7nlEZzy689dD2r4m | C13: SMINV_3.1 | D13: exploreArticleCard | E13: 2023-07-28T22:01:57.710Z | F13: topic-smart-investing | G13: topic-stock
A14: Sharing your money – it’s a life moment | B14: UvrcaNa1cwMe969OptsKb | C14: LM_COM_2.1 | D14: exploreArticleCard | E14: 2023-07-28T22:01:15.655Z | F14: topic-combining-finances | G14: lm-combining-finances
A15: Ways to combine your finances | B15: 46hjcn1OzNf5GE3haVHqNg | C15: LM_COM_1.1 | D15: exploreArticleCard | E15: 2023-07-28T00:43:13.695Z | F15: topic-combining-finances | G15: lm-combining-finances | H15: story-combining-finances | I15: collection-goals-101 | J15: collection-combining-finances
A16: Goals: What are they? Why do they matter? | B16: fufOxWn3qSC6N8lCPEArb | C16: GOAL_1.1 | D16: exploreArticleCard | E16: 2023-07-25T22:33:55.940Z | F16: topic-competing-goals | G16: collection-goals-101
A17: Caring for teens with Cleo | B17: 1t7PMBzjZvmyyMBNqIwe5O | C17: BEN23_2.2 | D17: exploreBenefitCard | E17: 2023-07-25T22:31:50.972Z | F17: topic-kids-education | G17: topic-growing-your-family
A18: Is now a good time to invest? | B18: 6c21mg94YY9xqv3xNRCF6b | C18: SMINV_1.9 | D18: exploreArticleCard | E18: 2023-07-21T19:56:29.201Z | F18: topic-smart-investing | G18: Smart investing - collection
A19: How to make money in a downturn market | B19: 27qsF992ZH4QiAcAhG2dOB | C19: SMINV_1.12 | D19: exploreArticleCard | E19: 2023-07-21T19:46:50.038Z | F19: topic-smart-investing | G19: Smart investing - collection
A20: Market volatility: How to navigate | B20: 4AVBAIJEUPBkrXOgCyHhGC | C20: SMINV_1.11 | D20: exploreArticleCard | E20: 2023-07-21T19:45:56.099Z | F20: topic-smart-investing | G20: Smart investing - collection
A21: Can you time the market? | B21: 10hEZDS9HPFQI88Dy49DTh | C21: SMINV_1.10 | D21: exploreArticleCard | E21: 2023-07-21T19:45:37.766Z | F21: topic-smart-investing | G21: Smart investing - collection
A22: Why should you invest? | B22: 3q3tsXFp5W4eSMo4yFGXJh | C22: SMINV_1.8 | D22: exploreArticleCard | E22: 2023-07-21T19:44:48.953Z | F22: topic-smart-investing | G22: Smart investing - collection
A23: Define your target number | B23: 7cSZtBYtkbyVT6P2o43ibs | C23: RET_1.3 | D23: exploreArticleCard | E23: 2023-07-21T19:39:34.515Z | F23: topic-retirement | G23: goal-retirement | H23: collection-vision-retirement | I23: collection-retirement | J23: collection-build-vision
A24: Common barriers to saving | B24: 1uEkmd8hDB1fPrHMXux21T | C24: RET_1.2 | D24: exploreArticleCard | E24: 2023-07-21T19:39:06.623Z | F24: topic-retirement | G24: goal-retirement | H24: story-retirement | I24: collection-retirement
A25: Retiring on your own terms | B25: 7vvkK5XEvXpA8tIDWNQlnH | C25: RET_1.1 | D25: exploreArticleCard | E25: 2023-07-21T19:38:22.974Z | F25: topic-retirement | G25: goal-retirement | H25: collection-vision-retirement | I25: collection-retirement
A26: 401(k) basics | B26: FFeCJfv5l1vOMoK7jPcKg | C26: RET_1.5 | D26: exploreArticleCard | E26: 2023-07-21T19:35:48.966Z | F26: topic-retirement | G26: topic-401(k) | H26: topic-401 | I26: topic-401k | J26: goal-retirement | K26: collection-vision-retirement | L26: collection-retirement
A27: Is a 401(k) loan a good option? | B27: 1vdq8TQD1jqGJJvX3Wn53o | C27: RET_1.8 | D27: exploreArticleCard | E27: 2023-07-21T19:35:14.048Z | F27: topic-retirement | G27: topic-401(k) | H27: topic-loans | I27: topic-401 | J27: topic-401k | K27: goal-retirement | L27: collection-401(k)-withdrawals-retirement | M27: collection-retirement
A28: Your Fidelity 401(k) options | B28: 37K6qv3YXJWe5lc4geHKqv | C28: RET_1.6 | D28: exploreBenefitCard | E28: 2023-07-21T19:34:11.410Z | F28: topic-retirement | G28: topic-401 | H28: topic-401k | I28: goal-retirement | J28: story-retirement | K28: benefit-fidelity-401(k)
A29: 401(k) news: friend or foe? | B29: 7lFtpVjgylBO9lWx6xsLkf | C29: BEN23_1.3 | D29: exploreArticleCard | E29: 2023-07-21T19:09:03.389Z | F29: topic-retirement | G29: topic-401(k) | H29: topic-401 | I29: topic-401k | J29: collection-meta-benefits
A30: New 401(k) and IRA maxes for 2023 | B30: 5xjza1fH94s5LckPzkl6VD | C30: RET_1.11 | D30: exploreArticleCard | E30: 2023-07-21T19:07:17.249Z | F30: topic-retirement | G30: topic-401(k) | H30: topic-ira | I30: topic-roth-ira | J30: topic-401 | K30: topic-match
A31: Small steps to a healthier future | B31: 2n6ebhc1JmSHRjq1hlqEAc | C31: BEN23_2.1 | D31: exploreBenefitCard | E31: 2023-07-17T19:57:36.293Z | F31: topic-mental-health | G31: topic-health
A32: July: recharge with self-care | B32: 40VkV7JkiFDi95pLlBpt1A | C32: TT23_1.7 | D32: exploreArticleCard | E32: 2023-07-17T19:53:32.572Z | F32: topic-health
A33: Feeling overwhelmed? Get support from Lyra | B33: 4EsmZO7BgpndMdnjSkEEzo | C33: DEB_1.6 | D33: exploreBenefitCard | E33: 2023-07-10T23:02:30.493Z | F33: topic-debt | G33: topic-lyra | H33: goal-debt-management | I33: benefit-lyra-mental-health | J33: benefit-people-portal | K33: collection-meta-benefits
A34: Stocks: how to find the real value | B34: 6AgPLGxufTjPh3N8GCYbLb | C34: SMINV_2.9 | D34: exploreArticleCard | E34: 2023-07-10T19:59:21.018Z | F34: topic-smart-investing | G34: topic-stock
A35: Spending too little, saving too much? | B35: 3VO3MiHsCUD5Ohyz42yD5K | C35: EMF_2.2 | D35: exploreArticleCard | E35: 2023-07-10T19:57:50.894Z | F35: topic-savings-account
A36: What’s the move in AI? | B36: 3jHoKvOolfJqWtewpEDxV | C36: SMINV_2.10 | D36: exploreArticleCard | E36: 2023-07-10T19:55:56.000Z | F36: topic-smart-investing | G36: topic-stock
A37: Estate planning for everyone | B37: 6LItN1K4USGOcLBAoJkV1K | C37: EST_1.3 | D37: exploreArticleCard | E37: 2023-07-10T19:54:13.723Z | F37: benefit-estate-planning
A38: Investing practice: how to manage market risk | B38: 3fwrSLeQqao4pZHzCSYOGZ | C38: Entry Point Simulator | D38: simulatorContent | E38: 2023-07-10T15:11:26.765Z | F38: topic-smart-investing | G38: topic-stock
A39: 401(k) conversions: how they work | B39: 7gq8ye9mIQBOlSNZ4mGz8u | C39: BEN23_1.10 | D39: exploreBenefitCard | E39: 2023-07-07T13:49:20.296Z | F39: topic-401(k) | G39: topic-roth-ira | H39: topic-401 | I39: topic-401k
A40: Buying a car: what to know | B40: 7oATLbHlAL221cMeVUAoy6 | C40: LM_RELO_1.2 | D40: exploreArticleCard | E40: 2023-07-06T18:33:44.675Z | F40: topic-relocation | G40: lm-relocation | H40: collection-relocating
A41: How do you spend your money? | B41: 5i5l5RZOK9b7TQyIdXLHMs | C41: EMF_2.1 | D41: exploreArticleCard | E41: 2023-07-06T18:28:45.295Z | F41: topic-savings-account
A42: Dark mode in Paven | B42: 7LruOTbnyAbZDeOhEh6b5E | C42: video_MayCampaignTrailer | D42: exploreVideoCard | E42: 2023-07-05T22:40:24.525Z | F42: collection-timely-topics
A43: What should I know about the process? | B43: 1imCcMUQxjvLx1zvqYQL3k | C43: LI_1.3 | D43: exploreArticleCard | E43: 2023-07-05T13:37:41.215Z | F43: Life Insurance- topic | G43: Life Insurance - collection | H43: Life Insurance - story
A44: Budgeting for closing costs | B44: 4ldWkP5iN82XyKPx70OIsL | C44: BAH_1.5 | D44: exploreArticleCard | E44: 2023-07-04T18:23:29.694Z | F44: topic-budget | G44: topic-housing | H44: goal-buying-a-home | I44: collection-buying-a-home
A45: Your RSUs: Basics of restricted stock units | B45: 1P13uxOOyCx9Fik6t52DK7 | C45: RSU_1.1 | D45: exploreBenefitCard | E45: 2023-07-03T16:02:02.356Z | F45: topic-rsus | G45: topic-vesting | H45: topic-restricted | I45: topic-stock | J45: topic-rsu | K45: topic-vest | L45: topic-schwab | M45: topic-charles | N45: collection-meta-benefits
A46: Your RSUs: Taxes on restricted stock units | B46: 38bNEAdm4WZn9jtUZP91nV | C46: RSU_1.3 | D46: exploreArticleCard | E46: 2023-07-03T16:01:02.791Z | F46: topic-taxes | G46: topic-vesting | H46: topic-restricted | I46: topic-stock | J46: topic-rsu | K46: topic-vest | L46: topic-schwab | M46: topic-charles
A47: How to boost emergency funds | B47: 7qXkRnZzobZjwtH2EMEerV | C47: EMF_1.6 | D47: exploreArticleCard | E47: 2023-06-16T20:44:59.255Z | F47: topic-emergency-fund | G47: goal-emergency-fund | H47: collection-emergency-fund
A48: Setting up automatic transfers | B48: 5lKy8OxVNCgejG7EfH3fKD | C48: EMF_1.5 | D48: exploreArticleCard | E48: 2023-06-16T20:37:30.726Z | F48: topic-emergency-fund | G48: topic-automatic-transfers | H48: goal-emergency-fund | I48: collection-emergency-fund
A49: Stocks with staying power | B49: HXowITNK4984Sui2euL0h | C49: SMINV_2.6 | D49: exploreArticleCard | E49: 2023-06-14T17:57:40.154Z | F49: topic-smart-investing | G49: Smart investing - collection | H49: topic-stock
A50: June: how to travel smart | B50: 3oGUJCzpqo1VJHViXAXikB | C50: BEN23_1.9 | D50: exploreBenefitCard | E50: 2023-06-09T21:41:36.647Z | F50: topic-travel | G50: collection-meta-benefits
A51: When should you buy a home? | B51: 1bnU0IlpXboAmaOQcjI9vp | C51: BAH_2.2 | D51: exploreArticleCard | E51: 2023-06-09T03:38:43.786Z | F51: topic-buying-a-home | G51: goal-buying-a-home | H51: collection-buying-a-home
A52: Home buying: starting your journey | B52: 7JR0r8UbRsSnOzjVrIFRco | C52: BAH_2.1 | D52: exploreArticleCard | E52: 2023-06-07T19:46:25.838Z | F52: topic-buying-a-home | G52: goal-buying-a-home | H52: collection-buying-a-home
A53: Estate planning: getting started | B53: 7v5rl31FZ0PsuMYNzrMbk | C53: EST_1.2 | D53: exploreArticleCard | E53: 2023-06-06T20:41:57.777Z | F53: benefit-estate-planning
A54: June: riding the inflation wave | B54: rKBG0drgx3kcZ1Rw3RGTW | C54: TT23_1.6 | D54: exploreArticleCard | E54: 2023-06-06T19:50:18.637Z | F54: topic-inflation | G54: collection-timely-topics
A55: Contrarian play: semiconductors | B55: 69UF4T9T37ZJgjLcueyCJN | C55: SMINV_2.7 | D55: exploreArticleCard | E55: 2023-05-26T18:59:45.375Z | F55: topic-smart-investing
A56: The power of compounding interest | B56: 7MJHtQVMn3oHeuyZYZ7LrB | C56: The power of compounding interest | D56: simulatorContent | E56: 2023-05-24T16:21:59.342Z | F56: topic-retirement | G56: topic-budget | H56: topic-compounding | I56: topic-simulator-compounding | J56: simulator-retirement
A57: Refocus 529 funds with Roth IRA transfers | B57: 6JB7mIvY7CrCOMBNAI59E6 | C57: TAX_1.4 | D57: exploreBenefitCard | E57: 2023-05-24T16:04:31.205Z | F57: topic-roth-ira | G57: topic-529 | H57: topic-taxes | I57: topic-tax-consultant
A58: Tax advice: what to expect this year | B58: 3BehwnZBBHKN2qxV9ZW8Wg | C58: TAX_1.3 | D58: exploreBenefitCard | E58: 2023-05-24T16:00:05.902Z | F58: topic-taxes
A59: New 401(k) rules to leave your worries behind | B59: MTBHCbxOVN1mhjCI4Gi9U | C59: BEN23_1.4 | D59: exploreBenefitCard | E59: 2023-05-24T15:56:49.498Z | F59: topic-401(k) | G59: topic-financial-coach | H59: topic-401 | I59: topic-401k | J59: benefit-financial-coach | K59: benefit-fidelity-401(k)
A60: Wellness reimbursement in 2023 | B60: 34nlgdxtAqTq2Z8Z3WDxBh | C60: BEN23_1.1 | D60: exploreBenefitCard | E60: 2023-05-24T15:45:31.208Z | F60: collection-meta-benefits
A61: College coaching from Bright Horizons | B61: 7yvOMQbfERtvQcFITk8PkD | C61: MM_1.7 | D61: exploreBenefitCard | E61: 2023-05-24T15:17:54.562Z | F61: topic-kids-education | G61: topic-financial-coach | H61: benefit-financial-coach | I61: benefit-misc | J61: benefit-bright-horizons | K61: collection-meta-benefits
A62: May: is there value in cash? | B62: 3Q0zXwmtXrfHBEC8phxJZM | C62: TT23_1.5 | D62: exploreArticleCard | E62: 2023-05-15T21:38:21.275Z | F62: topic-smart-investing | G62: collection-timely-topics
A63: Get help from a College Coach | B63: 4xTEkqpawqZXQGOQCJmjVl | C63: Get help from a College Coach | D63: exploreArticleCard | E63: 2023-05-11T20:18:20.214Z | F63: topic-kids-education | G63: topic-financial-coach | H63: goal-kids-education | I63: collection-fb-benefits | J63: collection-kids-education
A64: Other ways to save for education | B64: 6T84VV9e9fDftdKikDRksz | C64: SFC_1.7 | D64: exploreArticleCard | E64: 2023-05-11T20:14:38.735Z | F64: topic-kids-education | G64: goal-kids-education | H64: story-kids-education | I64: collection-advanced-strategies | J64: collection-kids-education
A65: Using a brokerage account to save | B65: 7rKjk2k5RiPMLiKRcoXrZ1 | C65: SFC_1.6 | D65: exploreArticleCard | E65: 2023-05-11T20:12:12.293Z | F65: topic-kids-education | G65: topic-brokerage-account | H65: goal-kids-education | I65: story-kids-education | J65: collection-advanced-strategies | K65: collection-kids-education
A66: Using a Roth IRA to save | B66: CZcZvvvFjtJcHiHM3DzN8 | C66: SFC_1.5 | D66: exploreArticleCard | E66: 2023-05-11T20:09:14.136Z | F66: topic-kids-education | G66: topic-roth-ira | H66: story-kids-education | I66: collection-account-types | J66: collection-kids-education
A67: The 529 plan, explained | B67: 5QCbiymJdeZtNQV75taLwk | C67: SFC_1.4 | D67: exploreArticleCard | E67: 2023-05-11T20:06:39.295Z | F67: topic-kids-education | G67: topic-529 | H67: goal-kids-education | I67: collection-account-types | J67: collection-kids-education
A68: Education account types | B68: 6Y95jlQhFRWdOUFnt4Egm | C68: SFC_1.3 | D68: exploreArticleCard | E68: 2023-05-11T20:01:45.091Z | F68: topic-kids-education | G68: goal-kids-education | H68: story-kids-education | I68: collection-account-types | J68: collection-kids-education
A69: Kids’ education vs other goals | B69: 1U9OyuMCKBJaDh4zxCkuiA | C69: SFC_1.2 | D69: exploreArticleCard | E69: 2023-05-11T19:58:22.386Z | F69: topic-kids-education | G69: goal-kids-education | H69: story-kids-education | I69: collection-kids-education
A70: Track your debt payments | B70: btv3P3YdkxNf0zqcwEAH4 | C70: DEB_1.8 | D70: exploreArticleCard | E70: 2023-05-11T18:55:55.683Z | F70: topic-debt | G70: goal-debt-management | H70: story-debt-management | I70: collection-managing-debt | J70: collection-debt
A71: Credit scores 101 | B71: 1NZMCPBnYrfE3v0M9fSXt4 | C71: DEB_1.7 | D71: exploreArticleCard | E71: 2023-05-11T18:35:40.137Z | F71: topic-credit-cards | G71: topic-credit-score | H71: collection-goals-101 | I71: collection-credit-card-debt | J71: collection-managing-debt | K71: collection-debt
A72: Refinance your student loans with Sofi & Earnest | B72: 3iNseJtkBv6m5HNQV8QjDC | C72: DEB_1.5 | D72: exploreBenefitCard | E72: 2023-05-11T18:30:49.984Z | F72: topic-debt | G72: topic-student-loans | H72: topic-refinancing | I72: benefit-sofi-earnest | J72: collection-meta-benefits
A73: Tips to cut credit card debt | B73: 31poVSYMQMCbeM2FQofIRi | C73: DEB_1.4 | D73: exploreArticleCard | E73: 2023-05-11T18:21:41.161Z | F73: topic-debt | G73: topic-credit-cards | H73: topic-credit-score | I73: goal-debt-management | J73: collection-goals-101 | K73: collection-credit-card-debt | L73: collection-managing-debt | M73: collection-debt
A74: How credit card debt works | B74: 5hayL3vE1ypoDE8ELKcbtJ | C74: DEB_1.3 | D74: exploreArticleCard | E74: 2023-05-11T18:18:35.983Z | F74: topic-debt | G74: topic-credit-cards | H74: topic-credit-score | I74: goal-debt-management | J74: collection-credit-card-debt | K74: collection-managing-debt | L74: collection-debt
A75: Dealing with student loan debt | B75: 6Eee9pQ3rSkCdLJnUBahVT | C75: DEB_1.2 | D75: exploreArticleCard | E75: 2023-05-11T18:14:56.848Z | F75: topic-debt | G75: goal-debt-management | H75: story-debt-management | I75: collection-goals-101 | J75: collection-student-loans | K75: collection-managing-debt | L75: collection-debt
A76: Meta's 401(k) match in 2023 | B76: 4m9ObHleGYAHetpJwNzLRF | C76: Company_Match_META 2023 | D76: simulatorContent | E76: 2023-05-11T17:31:02.092Z | F76: topic-401(k) | G76: topic-simulator-company-match | H76: topic-match
A77: Add your post-retirement work | B77: lwALm8GoRRB2UNy66fjhy | C77: RET_1.4 | D77: exploreArticleCard | E77: 2023-05-11T16:35:53.515Z | F77: topic-retirement | G77: goal-retirement | H77: story-retirement | I77: collection-vision-retirement | J77: collection-retirement | K77: collection-advanced-strategies
A78: Travel today and save for tomorrow | B78: 3ZweQAOsrsqgm28SCZF09Q | C78: TF_1.1 | D78: exploreArticleCard | E78: 2023-05-10T17:59:13.066Z | F78: topic-travel | G78: topic-travel-fund | H78: goal-saving-for-travel | I78: collection-travel-fund
A79: Good debt vs bad debt | B79: 2ActWmf1Hdnh80tgVgUiJ3 | C79: DEB_1.1 | D79: exploreArticleCard | E79: 2023-05-10T17:52:51.149Z | F79: topic-debt | G79: goal-debt-management | H79: story-debt-management | I79: collection-credit-card-debt | J79: collection-managing-debt | K79: collection-debt
A80: Do I need an emergency fund? | B80: 3XIA1q18lV1NZXHVhmUVfV | C80: EMF_1.1 | D80: exploreArticleCard | E80: 2023-05-10T16:37:05.317Z | F80: topic-emergency-fund | G80: goal-emergency-fund | H80: collection-emergency-fund
A81: 3 reasons to start saving now | B81: 2YEbx95wNuqCh5IS2Z6Mi9 | C81: SFC_1.1 | D81: exploreArticleCard | E81: 2023-05-10T16:23:05.880Z | F81: topic-kids-education | G81: goal-kids-education | H81: story-kids-education | I81: collection-goals-101 | J81: collection-build-vision | K81: collection-kids-education
A82: Save for emergencies or send money home? | B82: 7MiY8sNHiCZuc076FEazOe | C82: LM_RELO_1.3 | D82: exploreArticleCard | E82: 2023-05-10T14:56:33.446Z | F82: topic-emergency-fund | G82: topic-relocation | H82: collection-balacing-goals | I82: collection-relocating
A83: Making the most of your HSA | B83: ayHeah7fCUQWdWf5sONVQ | C83: HSA_1.4 | D83: exploreBenefitCard | E83: 2023-05-09T19:05:58.858Z | F83: topic-hsa
A84: Contrarian play: energy vs fuel stocks | B84: 7rHdxtIOKl9vahwgShViyP | C84: SMINV_2.5 | D84: exploreArticleCard | E84: 2023-05-08T01:15:16.951Z | F84: topic-smart-investing | G84: topic-stock
A85: Debt: how do you make progress? | B85: tqFTtOIQPrXOcvksLcj3B | C85: DEB23_1.2 | D85: exploreArticleCard | E85: 2023-05-05T19:59:18.128Z | F85: topic-debt | G85: goal-debt-management
A86: All about hidden mortgage fees | B86: 3ItjYdwrHmUCGRlJUbQLLP | C86: BAH_1.12 | D86: exploreArticleCard | E86: 2023-05-05T19:52:35.510Z | F86: topic-mortgage | G86: topic-housing | H86: goal-buying-a-home | I86: collection-buying-a-home
A87: Choosing your loan | B87: 6XTp2t7IOtrIdmBKZnGGRL | C87: BAH_1.11 | D87: exploreArticleCard | E87: 2023-05-05T19:49:29.096Z | F87: topic-loans | G87: topic-housing | H87: goal-buying-a-home | I87: collection-buying-a-home
A88: Kid costs vs debt | B88: 4VSAjivU2szW3SyExywFlH | C88: GYF_1.8 | D88: exploreArticleCard | E88: 2023-05-05T19:40:16.958Z | F88: topic-growing-your-family | G88: lm-growing-your-family
A89: Baby costs vs retirement? | B89: 1JjEettM33ku180YSbbqIx | C89: GYF_1.7 | D89: exploreArticleCard | E89: 2023-05-05T19:37:36.381Z | F89: topic-growing-your-family | G89: lm-growing-your-family | H89: collection-growing-your-family
A90: Egg freezing & IVF costs | B90: 7pegEm7RLBnHDZTUcffUyT | C90: GYF_1.5 | D90: exploreArticleCard | E90: 2023-05-05T19:33:16.505Z | F90: topic-growing-your-family | G90: lm-growing-your-family | H90: benefit-family-care-support | I90: benefit-family-assistance | J90: collection-growing-your-family
A91: Adoption costs | B91: 27HwQxOelFmNU9Z9PlIi9t | C91: GYF_1.3 | D91: exploreArticleCard | E91: 2023-05-05T19:28:48.841Z | F91: topic-growing-your-family | G91: lm-growing-your-family | H91: benefit-misc | I91: benefit-family-assistance | J91: collection-growing-your-family
A92: Life Insurance: is it time? | B92: 7zTpUZJ7Ct0NdhwEfpjrcW | C92: LI_2.3 | D92: exploreBenefitCard | E92: 2023-05-05T19:16:59.199Z | F92: Life Insurance- topic | G92: Life Insurance - collection | H92: Life Insurance - story
A93: Meta & baby benefits | B93: 4FHfNBt0AtjLx2IRkaJk0G | C93: GYF_1.12 | D93: exploreArticleCard | E93: 2023-05-05T19:12:20.071Z | F93: topic-growing-your-family | G93: lm-growing-your-family | H93: collection-meta-benefits
A94: May dates for Metamates | B94: 4Fi7sXj4Ct2JLJGacTZCvY | C94: BEN23_1.8 | D94: exploreBenefitCard | E94: 2023-05-05T18:52:32.464Z | F94: topic-rsus | G94: topic-hsa | H94: topic-rsu | I94: collection-meta-benefits
A95: Setting your kid up for future success | B95: 3hojfRCz5EwIG4gmFoyjf7 | C95: GYF_1.10 | D95: exploreArticleCard | E95: 2023-05-05T18:44:28.703Z | F95: topic-growing-your-family | G95: lm-growing-your-family | H95: collection-growing-your-family
A96: Defining your budget | B96: 5m7zbYKNpNemoOdm3ZPkD | C96: HOME_1.1 | D96: exploreArticleCard | E96: 2023-05-05T18:28:35.128Z | F96: topic-budget | G96: topic-welcome | H96: collection-get-started
A97: Your path to financial well-being | B97: 45Ha7B6FGI6PtYJYOgNszp | C97: HOME_0.0 | D97: exploreArticleCard | E97: 2023-05-05T18:07:20.813Z | F97: topic-welcome | G97: collection-get-started
A98: Look at your Life Path | B98: 2T75y0i1GYL1bNPtNd4vm | C98: HOME_1.2 | D98: exploreArticleCard | E98: 2023-05-05T18:01:13.941Z | F98: topic-welcome | G98: collection-get-started
A99: Learn about life moments | B99: 7hSCdXiTHVGNWf5enWm5mG | C99: HOME_1.3 | D99: exploreArticleCard | E99: 2023-05-05T17:58:56.100Z | F99: topic-welcome | G99: collection-get-started
A100: Discussing debt with your partner | B100: 79vPP4COjyo01YVYK0CMHl | C100: LM_COM_1.3 | D100: exploreArticleCard | E100: 2023-05-05T17:52:34.202Z | F100: topic-debt | G100: topic-combining-finances | H100: lm-combining-finances | I100: collection-combining-finances
...

Sheet Count of Unique tags
A1: Investing | B1: topic-smart-investing | E1: =COUNTIF('Export of publications with tag'!$F$2:$U$197,B1) -> 42
A2: Investing | B2: Smart investing - collection | C2: topic-stock | D2: topic-smart-investing | E2: =COUNTIF('Export of publications with tag'!$F$2:$U$197,B2) -> 22
A3: Investing | B3: topic-stock | E3: =COUNTIF('Export of publications with tag'!$F$2:$U$197,B3) -> 17
A4: Debt | B4: topic-debt | E4: =COUNTIF('Export of publications with tag'!$F$2:$U$197,B4) -> 17
A5: Benefits | B5: collection-meta-benefits | C5: collection-fb-benefits | E5: =COUNTIF('Export of publications with tag'!$F$2:$U$197,B5) -> 16 | F5: duplicates
A6: Retirement | B6: topic-retirement | E6: =COUNTIF('Export of publications with tag'!$F$2:$U$197,B6) -> 16
A7: Housing | B7: collection-buying-a-home | E7: =COUNTIF('Export of publications with tag'!$F$2:$U$197,B7) -> 15
A8: Housing | B8: goal-buying-a-home | E8: =COUNTIF('Export of publications with tag'!$F$2:$U$197,B8) -> 15
A9: Housing | B9: topic-housing | E9: =COUNTIF('Export of publications with tag'!$F$2:$U$197,B9) -> 14
A10: Family | B10: topic-growing-your-family | E10: =COUNTIF('Export of publications with tag'!$F$2:$U$197,B10) -> 13
A11: Family | B11: lm-growing-your-family | E11: =COUNTIF('Export of publications with tag'!$F$2:$U$197,B11) -> 12
A12: Emergency fund | B12: topic-emergency-fund | E12: =COUNTIF('Export of publications with tag'!$F$2:$U$197,B12) -> 12
A13: Retirement | B13: collection-retirement | E13: =COUNTIF('Export of publications with tag'!$F$2:$U$197,B13) -> 11
A14: Markets | B14: topic-inflation | E14: =COUNTIF('Export of publications with tag'!$F$2:$U$197,B14) -> 11
A15: Debt | B15: goal-debt-management | E15: =COUNTIF('Export of publications with tag'!$F$2:$U$197,B15) -> 10
A16: Account types | B16: topic-401 | E16: =COUNTIF('Export of publications with tag'!$F$2:$U$197,B16) -> 10
A17: Account types | B17: topic-401(k) | C17: topic-401 | D17: topic-401k | E17: =COUNTIF('Export of publications with tag'!$F$2:$U$197,B17) -> 10
A18: Budget - Extras | B18: topic-travel | C18: collection-travel-fund | E18: =COUNTIF('Export of publications with tag'!$F$2:$U$197,B18) -> 10
A19: Kids Education | B19: topic-kids-education | E19: =COUNTIF('Export of publications with tag'!$F$2:$U$197,B19) -> 10
A20: Debt | B20: collection-debt | E20: =COUNTIF('Export of publications with tag'!$F$2:$U$197,B20) -> 9
A21: App | B21: collection-goals-101 | E21: =COUNTIF('Export of publications with tag'!$F$2:$U$197,B21) -> 9
A22: Kids Education | B22: collection-kids-education | E22: =COUNTIF('Export of publications with tag'!$F$2:$U$197,B22) -> 9
A23: Account types | B23: topic-401k | E23: =COUNTIF('Export of publications with tag'!$F$2:$U$197,B23) -> 9
A24: Budget - Extras | B24: topic-travel-fund | E24: =COUNTIF('Export of publications with tag'!$F$2:$U$197,B24) -> 9
A25: App | B25: collection-timely-topics | E25: =COUNTIF('Export of publications with tag'!$F$2:$U$197,B25) -> 9
A26: Family | B26: collection-growing-your-family | E26: =COUNTIF('Export of publications with tag'!$F$2:$U$197,B26) -> 8
A27: Debt | B27: collection-managing-debt | E27: =COUNTIF('Export of publications with tag'!$F$2:$U$197,B27) -> 8
A28: Budget - Extras | B28: collection-travel-fund | E28: =COUNTIF('Export of publications with tag'!$F$2:$U$197,B28) -> 8
A29: Retirement | B29: goal-retirement | E29: =COUNTIF('Export of publications with tag'!$F$2:$U$197,B29) -> 8
A30: Budget - Extras | B30: goal-saving-for-travel | E30: =COUNTIF('Export of publications with tag'!$F$2:$U$197,B30) -> 8
... A49: Benefits | B49: topic-match | E49: =COUNTIF('Export of publications with tag'!$F$2:$U$197,B49) -> 5
A50: Income | B50: topic-rsu | C50: topic-restricted | D50: topic-rsus | E50: =COUNTIF('Export of publications with tag'!$F$2:$U$197,B50) -> 5
A51: Income | B51: topic-starting-side-hustle | E51: =COUNTIF('Export of publications with tag'!$F$2:$U$197,B51) -> 5
A52: Account types | B52: topic-hsa | E52: =COUNTIF('Export of publications with tag'!$F$2:$U$197,B52) -> 5
A53: Account types | B53: topic-roth-ira | E53: =COUNTIF('Export of publications with tag'!$F$2:$U$197,B53) -> 5
A54: Budget | B54: topic-budget | E54: =COUNTIF('Export of publications with tag'!$F$2:$U$197,B54) -> 5
A55: ?? | B55: topic-relocation | E55: =COUNTIF('Export of publications with tag'!$F$2:$U$197,B55) -> 5
A56: App | B56: topic-welcome | E56: =COUNTIF('Export of publications with tag'!$F$2:$U$197,B56) -> 5
A57: Income | B57: topic-side-hustle | E57: =COUNTIF('Export of publications with tag'!$F$2:$U$197,B57) -> 5
A58: Account types | B58: benefit-fidelity-401(k) | E58: =COUNTIF('Export of publications with tag'!$F$2:$U$197,B58) -> 4
A59: Benefits | B59: benefit-financial-coach | E59: =COUNTIF('Export of publications with tag'!$F$2:$U$197,B59) -> 4
A60: Benefits | B60: benefit-misc | E60: =COUNTIF('Export of publications with tag'!$F$2:$U$197,B60) -> 4
A61: Account types | B61: collection-account-types | E61: =COUNTIF('Export of publications with tag'!$F$2:$U$197,B61) -> 4
A62: App | B62: collection-get-started | E62: =COUNTIF('Export of publications with tag'!$F$2:$U$197,B62) -> 4
... A79: Income | B79: topic-schwab | E79: =COUNTIF('Export of publications with tag'!$F$2:$U$197,B79) -> 3
A80: Income | B80: topic-vest | E80: =COUNTIF('Export of publications with tag'!$F$2:$U$197,B80) -> 3 | F80: better than RSUs?
A81: Income | B81: topic-vesting | C81: topic-vest | E81: =COUNTIF('Export of publications with tag'!$F$2:$U$197,B81) -> 3
A82: ?? | B82: topic-competing-goals | E82: =COUNTIF('Export of publications with tag'!$F$2:$U$197,B82) -> 3
A83: Estate planning | B83: benefit-estate-planning | E83: =COUNTIF('Export of publications with tag'!$F$2:$U$197,B83) -> 3
A84: Investing | B84: topic-cryptocurrency | E84: =COUNTIF('Export of publications with tag'!$F$2:$U$197,B84) -> 3
A85: Income | B85: topic-rsus | E85: =COUNTIF('Export of publications with tag'!$F$2:$U$197,B85) -> 3
A86: Care | B86: benefit-family-care-support | E86: =COUNTIF('Export of publications with tag'!$F$2:$U$197,B86) -> 2
A87: Account types | B87: benefit-fsa | E87: =COUNTIF('Export of publications with tag'!$F$2:$U$197,B87) -> 2
A88: Account types | B88: collection-401(k)-withdrawals-retirement | E88: =COUNTIF('Export of publications with tag'!$F$2:$U$197,B88) -> 2
A89: ?? | B89: collection-quick-wins | E89: =COUNTIF('Export of publications with tag'!$F$2:$U$197,B89) -> 2
A90: Insurance | B90: Life Insurance - story | E90: =COUNTIF('Export of publications with tag'!$F$2:$U$197,B90) -> 2
A91: ?? | B91: lm-relocation | E91: =COUNTIF('Export of publications with tag'!$F$2:$U$197,B91) -> 2
A92: Retirement | B92: simulator-retirement | E92: =COUNTIF('Export of publications with tag'!$F$2:$U$197,B92) -> 2
A93: Couples | B93: story-combining-finances | E93: =COUNTIF('Export of publications with tag'!$F$2:$U$197,B93) -> 2
... A111: Care | B111: benefit-wellthy | E111: =COUNTIF('Export of publications with tag'!$F$2:$U$197,B111) -> 1
A112: Budget | B112: calc-budgeting | E112: =COUNTIF('Export of publications with tag'!$F$2:$U$197,B112) -> 1 | F112: What is this?
A113: Account types | B113: collection-401(k)-retirement | E113: =COUNTIF('Export of publications with tag'!$F$2:$U$197,B113) -> 1
A114: Health | B114: collection-covid | E114: =COUNTIF('Export of publications with tag'!$F$2:$U$197,B114) -> 1
A115: Benefits | B115: collection-fb-benefits | E115: =COUNTIF('Export of publications with tag'!$F$2:$U$197,B115) -> 1
A116: Income | B116: collection-rsus-retirement | E116: =COUNTIF('Export of publications with tag'!$F$2:$U$197,B116) -> 1
A117: Loans | B117: collection-student-loans | E117: =COUNTIF('Export of publications with tag'!$F$2:$U$197,B117) -> 1
A118: Emergency fund | B118: story-emergency-fund | E118: =COUNTIF('Export of publications with tag'!$F$2:$U$197,B118) -> 1
A119: Relocation | B119: story-relocation | E119: =COUNTIF('Export of publications with tag'!$F$2:$U$197,B119) -> 1
A120: Account types | B120: topic-after-tax-401(k) | E120: =COUNTIF('Export of publications with tag'!$F$2:$U$197,B120) -> 1
A121: Account types | B121: topic-automatic-transfers | E121: =COUNTIF('Export of publications with tag'!$F$2:$U$197,B121) -> 1
A122: Income | B122: topic-bonus | E122: =COUNTIF('Export of publications with tag'!$F$2:$U$197,B122) -> 1
A123: Account types | B123: topic-brokerage-account | E123: =COUNTIF('Export of publications with tag'!$F$2:$U$197,B123) -> 1
A124: ?? | B124: topic-compounding | E124: =COUNTIF('Export of publications with tag'!$F$2:$U$197,B124) -> 1
... A133: Mental health | B133: topic-mental-health | E133: =COUNTIF('Export of publications with tag'!$F$2:$U$197,B133) -> 1

Sheet Experiment - Topics->Tags
A1: Wealth strategies | B1: {=_xlfn.UNIQUE('Count of Unique tags'!A1:A133)} -> Investing | C1: =COUNTIF('Count of Unique tags'!A1:A133,B1) -> 5
B2: Debt | C2: =COUNTIF('Count of Unique tags'!A2:A134,B2) -> 5
A3: Benefits | B3: Benefits | C3: =COUNTIF('Count of Unique tags'!A3:A135,B3) -> 7
B4: Retirement | C4: =COUNTIF('Count of Unique tags'!A4:A136,B4) -> 6
B5: Housing | C5: =COUNTIF('Count of Unique tags'!A5:A137,B5) -> 5
B6: Family | C6: =COUNTIF('Count of Unique tags'!A6:A138,B6) -> 5 | D6: Couples
A7: Security | B7: Emergency fund | C7: =COUNTIF('Count of Unique tags'!A7:A139,B7) -> 4
B8: Markets | C8: =COUNTIF('Count of Unique tags'!A8:A140,B8) -> 1 | D8: ??
A9: Wealth strategies | B9: Account types | C9: =COUNTIF('Count of Unique tags'!A9:A141,B9) -> 22 | D9: break up?
A10: Gratification | B10: Budget - Extras | C10: =COUNTIF('Count of Unique tags'!A10:A142,B10) -> 4
B11: Kids Education | C11: =COUNTIF('Count of Unique tags'!A11:A143,B11) -> 5 | D11: ??
B12: App | C12: =COUNTIF('Count of Unique tags'!A12:A144,B12) -> 5
A13: Wealth strategies | B13: Taxes | C13: =COUNTIF('Count of Unique tags'!A13:A145,B13) -> 3
B14: Loans | C14: =COUNTIF('Count of Unique tags'!A14:A146,B14) -> 6
B15: Couples | C15: =COUNTIF('Count of Unique tags'!A15:A147,B15) -> 4 | D15: Family
B16: ?? | C16: =COUNTIF('Count of Unique tags'!A16:A148,B16) -> 14
B17: Credit | C17: =COUNTIF('Count of Unique tags'!A17:A149,B17) -> 3 | D17: Loans
A18: Security | B18: Health | C18: =COUNTIF('Count of Unique tags'!A18:A150,B18) -> 2
B19: Income | C19: =COUNTIF('Count of Unique tags'!A19:A151,B19) -> 13 | D19: break up - RSUs, bonus, side hustle
A20: Security | B20: Budget | C20: =COUNTIF('Count of Unique tags'!A20:A152,B20) -> 2
A21: Security | B21: Insurance | C21: =COUNTIF('Count of Unique tags'!A21:A153,B21) -> 3
B22: Estate planning | C22: =COUNTIF('Count of Unique tags'!A22:A154,B22) -> 1 | D22: Inheritance
B23: Care | C23: =COUNTIF('Count of Unique tags'!A23:A155,B23) -> 3
B24: Inheritance | C24: =COUNTIF('Count of Unique tags'!A24:A156,B24) -> 1 | D24: Family?
B25: Mental health | C25: =COUNTIF('Count of Unique tags'!A25:A157,B25) -> 3 | D25: Estates?
B26: Relocation | C26: =COUNTIF('Count of Unique tags'!A26:A158,B26) -> 1 | D26: Housing?
C27: =COUNTIF('Count of Unique tags'!A27:A159,B27) -> 0
C28: =COUNTIF('Count of Unique tags'!A28:A160,B28) -> 0
D33: group-saving-how ... how (mindset/strategy for finding the money), group-account-types ... where (account types), group-priortiies ... why (motivation, goal priorities)

Sheet Unique tags
A1: topic-caregiving
A2: topic-competing-goals
A3: topic-smart-investing
A4: topic-inflation
A5: topic-caregiving
A6: topic-inheritance
A7: collection-meta-benefits
A8: benefit-estate-planning
A9: topic-retirement
A10: Life Insurance- topic
A11: topic-smart-investing
A12: topic-smart-investing
... A80: topic-kids-education
A81: topic-emergency-fund | C81: collection-debt
A82: topic-hsa
A83: topic-smart-investing
A84: topic-debt
A85: topic-mortgage
A86: topic-loans
A87: topic-growing-your-family
A88: topic-growing-your-family
A89: topic-growing-your-family
A90: topic-growing-your-family
A91: Life Insurance- topic
A92: topic-growing-your-family
A93: topic-rsus
... A1178: collection-kids-education
